{"id":"RbV/","dependencies":[{"name":"/Users/carlos/dev/source/Staging/prototype/package.json","includedInParent":true,"mtime":1533239245440},{"name":"/Users/carlos/dev/source/Staging/prototype/.babelrc","includedInParent":true,"mtime":1533239245154}],"generated":{"js":"module.exports=\"/18ed3eab4fecbe5b21ba37178c63789f.woff\";","map":{"mappings":[{"source":"0","name":"module","original":{"line":1,"column":0},"generated":{"line":1,"column":0}},{"source":"0","name":"exports","original":{"line":1,"column":7},"generated":{"line":1,"column":7}},{"source":"0","original":{"line":1,"column":17},"generated":{"line":1,"column":15}}],"sources":{},"lineCount":null}},"hash":"8dde80d55fdf9828bfda5d2a1fb570d3","cacheData":{"env":{}}}