{"id":"wBew","dependencies":[{"name":"/Users/carlos/dev/source/Staging/prototype/node_modules/draft-js/package.json","includedInParent":true,"mtime":1529260753465},{"name":"/Users/carlos/dev/source/Staging/prototype/package.json","includedInParent":true,"mtime":1533239245440},{"name":"/Users/carlos/dev/source/Staging/prototype/.babelrc","includedInParent":true,"mtime":1533239245154},{"name":"./BlockMapBuilder","loc":{"line":16,"column":30},"parent":"/Users/carlos/dev/source/Staging/prototype/node_modules/draft-js/lib/insertFragmentIntoContentState.js","resolved":"/Users/carlos/dev/source/Staging/prototype/node_modules/draft-js/lib/BlockMapBuilder.js"},{"name":"./ContentBlockNode","loc":{"line":17,"column":31},"parent":"/Users/carlos/dev/source/Staging/prototype/node_modules/draft-js/lib/insertFragmentIntoContentState.js","resolved":"/Users/carlos/dev/source/Staging/prototype/node_modules/draft-js/lib/ContentBlockNode.js"},{"name":"immutable","loc":{"line":18,"column":24},"parent":"/Users/carlos/dev/source/Staging/prototype/node_modules/draft-js/lib/insertFragmentIntoContentState.js","resolved":"/Users/carlos/dev/source/Staging/prototype/node_modules/immutable/dist/immutable.js"},{"name":"./insertIntoList","loc":{"line":20,"column":29},"parent":"/Users/carlos/dev/source/Staging/prototype/node_modules/draft-js/lib/insertFragmentIntoContentState.js","resolved":"/Users/carlos/dev/source/Staging/prototype/node_modules/draft-js/lib/insertIntoList.js"},{"name":"fbjs/lib/invariant","loc":{"line":21,"column":24},"parent":"/Users/carlos/dev/source/Staging/prototype/node_modules/draft-js/lib/insertFragmentIntoContentState.js","resolved":"/Users/carlos/dev/source/Staging/prototype/node_modules/fbjs/lib/invariant.js"},{"name":"./randomizeBlockMapKeys","loc":{"line":22,"column":36},"parent":"/Users/carlos/dev/source/Staging/prototype/node_modules/draft-js/lib/insertFragmentIntoContentState.js","resolved":"/Users/carlos/dev/source/Staging/prototype/node_modules/draft-js/lib/randomizeBlockMapKeys.js"}],"generated":{"js":"\"use strict\";var e=require(\"./BlockMapBuilder\"),t=require(\"./ContentBlockNode\"),r=require(\"immutable\"),i=require(\"./insertIntoList\"),n=require(\"fbjs/lib/invariant\"),a=require(\"./randomizeBlockMapKeys\"),s=r.List,c=function(e,t,r,n,a,s){var c=r.get(a),g=c.getText(),o=c.getCharacterList(),l=a,f=s+n.getText().length,u=c.merge({text:g.slice(0,s)+n.getText()+g.slice(s),characterList:i(o,n.getCharacterList(),s),data:n.getData()});return e.merge({blockMap:r.set(a,u),selectionBefore:t,selectionAfter:t.merge({anchorKey:l,anchorOffset:f,focusKey:l,focusOffset:f,isBackward:!1})})},g=function(e,t,r){var i=e.getText(),n=e.getCharacterList(),a=i.slice(0,t),s=n.slice(0,t),c=r.first();return e.merge({text:a+c.getText(),characterList:s.concat(c.getCharacterList()),type:a?e.getType():c.getType(),data:c.getData()})},o=function(e,t,r){var i=e.getText(),n=e.getCharacterList(),a=i.length,s=i.slice(t,a),c=n.slice(t,a),g=r.last();return g.merge({text:g.getText()+s,characterList:g.getCharacterList().concat(c),data:g.getData()})},l=function(e,t){var r=e.getKey(),i=e,n=[];for(t.get(r)&&n.push(r);i&&i.getNextSiblingKey();){var a=i.getNextSiblingKey();if(!a)break;n.push(a),i=t.get(a)}return n},f=function(e,t,r,i){return e.withMutations(function(t){var n=r.getKey(),a=i.getKey(),c=r.getNextSiblingKey(),g=r.getParentKey(),o=l(i,e),f=o[o.length-1];if(t.get(a)?(t.setIn([n,\"nextSibling\"],a),t.setIn([a,\"prevSibling\"],n)):(t.setIn([n,\"nextSibling\"],i.getNextSiblingKey()),t.setIn([i.getNextSiblingKey(),\"prevSibling\"],n)),t.setIn([f,\"nextSibling\"],c),c&&t.setIn([c,\"prevSibling\"],f),o.forEach(function(e){return t.setIn([e,\"parent\"],g)}),g){var u=e.get(g).getChildKeys(),h=u.indexOf(n)+1,y=u.toArray();y.splice.apply(y,[h,0].concat(o)),t.setIn([g,\"children\"],s(y))}})},u=function(r,i,n,a,s,c){var l=n.first()instanceof t,u=[],h=a.size,y=n.get(s),p=a.first(),x=a.last(),K=x.getLength(),b=x.getKey(),d=l&&(!y.getChildKeys().isEmpty()||!p.getChildKeys().isEmpty());n.forEach(function(e,t){t===s?(d?u.push(e):u.push(g(e,c,a)),a.slice(d?0:1,h-1).forEach(function(e){return u.push(e)}),u.push(o(e,c,a))):u.push(e)});var m=e.createFromArray(u);return l&&(m=f(m,n,y,p)),r.merge({blockMap:m,selectionBefore:i,selectionAfter:i.merge({anchorKey:b,anchorOffset:K,focusKey:b,focusOffset:K,isBackward:!1})})},h=function(e,r,i){r.isCollapsed()||n(!1);var s=e.getBlockMap(),g=a(i),o=r.getStartKey(),l=r.getStartOffset(),f=s.get(o);return f instanceof t&&(f.getChildKeys().isEmpty()||n(!1)),1===g.size?c(e,r,s,g.first(),o,l):u(e,r,s,g,o,l)};module.exports=h;","map":{"mappings":[{"source":"../node_modules/draft-js/lib/insertFragmentIntoContentState.js","original":{"line":14,"column":0},"generated":{"line":1,"column":0}},{"source":"../node_modules/draft-js/lib/insertFragmentIntoContentState.js","original":{"line":16,"column":0},"generated":{"line":1,"column":13}},{"source":"../node_modules/draft-js/lib/insertFragmentIntoContentState.js","name":"BlockMapBuilder","original":{"line":16,"column":4},"generated":{"line":1,"column":17}},{"source":"../node_modules/draft-js/lib/insertFragmentIntoContentState.js","name":"require","original":{"line":16,"column":22},"generated":{"line":1,"column":19}},{"source":"../node_modules/draft-js/lib/insertFragmentIntoContentState.js","original":{"line":16,"column":30},"generated":{"line":1,"column":27}},{"source":"../node_modules/draft-js/lib/insertFragmentIntoContentState.js","name":"ContentBlockNode","original":{"line":17,"column":4},"generated":{"line":1,"column":48}},{"source":"../node_modules/draft-js/lib/insertFragmentIntoContentState.js","name":"require","original":{"line":17,"column":23},"generated":{"line":1,"column":50}},{"source":"../node_modules/draft-js/lib/insertFragmentIntoContentState.js","original":{"line":17,"column":31},"generated":{"line":1,"column":58}},{"source":"../node_modules/draft-js/lib/insertFragmentIntoContentState.js","name":"Immutable","original":{"line":18,"column":4},"generated":{"line":1,"column":80}},{"source":"../node_modules/draft-js/lib/insertFragmentIntoContentState.js","name":"require","original":{"line":18,"column":16},"generated":{"line":1,"column":82}},{"source":"../node_modules/draft-js/lib/insertFragmentIntoContentState.js","original":{"line":18,"column":24},"generated":{"line":1,"column":90}},{"source":"../node_modules/draft-js/lib/insertFragmentIntoContentState.js","name":"insertIntoList","original":{"line":20,"column":4},"generated":{"line":1,"column":103}},{"source":"../node_modules/draft-js/lib/insertFragmentIntoContentState.js","name":"require","original":{"line":20,"column":21},"generated":{"line":1,"column":105}},{"source":"../node_modules/draft-js/lib/insertFragmentIntoContentState.js","original":{"line":20,"column":29},"generated":{"line":1,"column":113}},{"source":"../node_modules/draft-js/lib/insertFragmentIntoContentState.js","name":"invariant","original":{"line":21,"column":4},"generated":{"line":1,"column":133}},{"source":"../node_modules/draft-js/lib/insertFragmentIntoContentState.js","name":"require","original":{"line":21,"column":16},"generated":{"line":1,"column":135}},{"source":"../node_modules/draft-js/lib/insertFragmentIntoContentState.js","original":{"line":21,"column":24},"generated":{"line":1,"column":143}},{"source":"../node_modules/draft-js/lib/insertFragmentIntoContentState.js","name":"randomizeBlockMapKeys","original":{"line":22,"column":4},"generated":{"line":1,"column":165}},{"source":"../node_modules/draft-js/lib/insertFragmentIntoContentState.js","name":"require","original":{"line":22,"column":28},"generated":{"line":1,"column":167}},{"source":"../node_modules/draft-js/lib/insertFragmentIntoContentState.js","original":{"line":22,"column":36},"generated":{"line":1,"column":175}},{"source":"../node_modules/draft-js/lib/insertFragmentIntoContentState.js","name":"List","original":{"line":24,"column":4},"generated":{"line":1,"column":202}},{"source":"../node_modules/draft-js/lib/insertFragmentIntoContentState.js","name":"Immutable","original":{"line":24,"column":11},"generated":{"line":1,"column":204}},{"source":"../node_modules/draft-js/lib/insertFragmentIntoContentState.js","name":"List","original":{"line":24,"column":21},"generated":{"line":1,"column":206}},{"source":"../node_modules/draft-js/lib/insertFragmentIntoContentState.js","name":"updateExistingBlock","original":{"line":27,"column":4},"generated":{"line":1,"column":211}},{"source":"../node_modules/draft-js/lib/insertFragmentIntoContentState.js","original":{"line":27,"column":26},"generated":{"line":1,"column":213}},{"source":"../node_modules/draft-js/lib/insertFragmentIntoContentState.js","name":"contentState","original":{"line":27,"column":55},"generated":{"line":1,"column":222}},{"source":"../node_modules/draft-js/lib/insertFragmentIntoContentState.js","name":"selectionState","original":{"line":27,"column":69},"generated":{"line":1,"column":224}},{"source":"../node_modules/draft-js/lib/insertFragmentIntoContentState.js","name":"blockMap","original":{"line":27,"column":85},"generated":{"line":1,"column":226}},{"source":"../node_modules/draft-js/lib/insertFragmentIntoContentState.js","name":"fragmentBlock","original":{"line":27,"column":95},"generated":{"line":1,"column":228}},{"source":"../node_modules/draft-js/lib/insertFragmentIntoContentState.js","name":"targetKey","original":{"line":27,"column":110},"generated":{"line":1,"column":230}},{"source":"../node_modules/draft-js/lib/insertFragmentIntoContentState.js","name":"targetOffset","original":{"line":27,"column":121},"generated":{"line":1,"column":232}},{"source":"../node_modules/draft-js/lib/insertFragmentIntoContentState.js","name":"targetBlock","original":{"line":28,"column":6},"generated":{"line":1,"column":235}},{"source":"../node_modules/draft-js/lib/insertFragmentIntoContentState.js","name":"targetBlock","original":{"line":28,"column":6},"generated":{"line":1,"column":239}},{"source":"../node_modules/draft-js/lib/insertFragmentIntoContentState.js","name":"blockMap","original":{"line":28,"column":20},"generated":{"line":1,"column":241}},{"source":"../node_modules/draft-js/lib/insertFragmentIntoContentState.js","name":"get","original":{"line":28,"column":29},"generated":{"line":1,"column":243}},{"source":"../node_modules/draft-js/lib/insertFragmentIntoContentState.js","name":"targetKey","original":{"line":28,"column":33},"generated":{"line":1,"column":247}},{"source":"../node_modules/draft-js/lib/insertFragmentIntoContentState.js","name":"text","original":{"line":29,"column":6},"generated":{"line":1,"column":250}},{"source":"../node_modules/draft-js/lib/insertFragmentIntoContentState.js","name":"targetBlock","original":{"line":29,"column":13},"generated":{"line":1,"column":252}},{"source":"../node_modules/draft-js/lib/insertFragmentIntoContentState.js","name":"getText","original":{"line":29,"column":25},"generated":{"line":1,"column":254}},{"source":"../node_modules/draft-js/lib/insertFragmentIntoContentState.js","name":"chars","original":{"line":30,"column":6},"generated":{"line":1,"column":264}},{"source":"../node_modules/draft-js/lib/insertFragmentIntoContentState.js","name":"targetBlock","original":{"line":30,"column":14},"generated":{"line":1,"column":266}},{"source":"../node_modules/draft-js/lib/insertFragmentIntoContentState.js","name":"getCharacterList","original":{"line":30,"column":26},"generated":{"line":1,"column":268}},{"source":"../node_modules/draft-js/lib/insertFragmentIntoContentState.js","name":"finalKey","original":{"line":31,"column":6},"generated":{"line":1,"column":287}},{"source":"../node_modules/draft-js/lib/insertFragmentIntoContentState.js","name":"targetKey","original":{"line":31,"column":17},"generated":{"line":1,"column":289}},{"source":"../node_modules/draft-js/lib/insertFragmentIntoContentState.js","name":"finalOffset","original":{"line":32,"column":6},"generated":{"line":1,"column":291}},{"source":"../node_modules/draft-js/lib/insertFragmentIntoContentState.js","name":"targetOffset","original":{"line":32,"column":20},"generated":{"line":1,"column":293}},{"source":"../node_modules/draft-js/lib/insertFragmentIntoContentState.js","name":"fragmentBlock","original":{"line":32,"column":35},"generated":{"line":1,"column":295}},{"source":"../node_modules/draft-js/lib/insertFragmentIntoContentState.js","name":"getText","original":{"line":32,"column":49},"generated":{"line":1,"column":297}},{"source":"../node_modules/draft-js/lib/insertFragmentIntoContentState.js","name":"length","original":{"line":32,"column":59},"generated":{"line":1,"column":307}},{"source":"../node_modules/draft-js/lib/insertFragmentIntoContentState.js","name":"newBlock","original":{"line":34,"column":6},"generated":{"line":1,"column":314}},{"source":"../node_modules/draft-js/lib/insertFragmentIntoContentState.js","name":"targetBlock","original":{"line":34,"column":17},"generated":{"line":1,"column":316}},{"source":"../node_modules/draft-js/lib/insertFragmentIntoContentState.js","name":"merge","original":{"line":34,"column":29},"generated":{"line":1,"column":318}},{"source":"../node_modules/draft-js/lib/insertFragmentIntoContentState.js","original":{"line":34,"column":35},"generated":{"line":1,"column":324}},{"source":"../node_modules/draft-js/lib/insertFragmentIntoContentState.js","name":"text","original":{"line":35,"column":10},"generated":{"line":1,"column":325}},{"source":"../node_modules/draft-js/lib/insertFragmentIntoContentState.js","name":"text","original":{"line":35,"column":10},"generated":{"line":1,"column":330}},{"source":"../node_modules/draft-js/lib/insertFragmentIntoContentState.js","name":"slice","original":{"line":35,"column":15},"generated":{"line":1,"column":332}},{"source":"../node_modules/draft-js/lib/insertFragmentIntoContentState.js","original":{"line":35,"column":21},"generated":{"line":1,"column":338}},{"source":"../node_modules/draft-js/lib/insertFragmentIntoContentState.js","name":"targetOffset","original":{"line":35,"column":24},"generated":{"line":1,"column":340}},{"source":"../node_modules/draft-js/lib/insertFragmentIntoContentState.js","name":"fragmentBlock","original":{"line":35,"column":40},"generated":{"line":1,"column":343}},{"source":"../node_modules/draft-js/lib/insertFragmentIntoContentState.js","name":"getText","original":{"line":35,"column":54},"generated":{"line":1,"column":345}},{"source":"../node_modules/draft-js/lib/insertFragmentIntoContentState.js","name":"text","original":{"line":35,"column":66},"generated":{"line":1,"column":355}},{"source":"../node_modules/draft-js/lib/insertFragmentIntoContentState.js","name":"slice","original":{"line":35,"column":71},"generated":{"line":1,"column":357}},{"source":"../node_modules/draft-js/lib/insertFragmentIntoContentState.js","name":"targetOffset","original":{"line":35,"column":77},"generated":{"line":1,"column":363}},{"source":"../node_modules/draft-js/lib/insertFragmentIntoContentState.js","name":"insertIntoList","original":{"line":36,"column":19},"generated":{"line":1,"column":366}},{"source":"../node_modules/draft-js/lib/insertFragmentIntoContentState.js","name":"insertIntoList","original":{"line":36,"column":19},"generated":{"line":1,"column":380}},{"source":"../node_modules/draft-js/lib/insertFragmentIntoContentState.js","name":"chars","original":{"line":36,"column":34},"generated":{"line":1,"column":382}},{"source":"../node_modules/draft-js/lib/insertFragmentIntoContentState.js","name":"fragmentBlock","original":{"line":36,"column":41},"generated":{"line":1,"column":384}},{"source":"../node_modules/draft-js/lib/insertFragmentIntoContentState.js","name":"getCharacterList","original":{"line":36,"column":55},"generated":{"line":1,"column":386}},{"source":"../node_modules/draft-js/lib/insertFragmentIntoContentState.js","name":"targetOffset","original":{"line":36,"column":75},"generated":{"line":1,"column":405}},{"source":"../node_modules/draft-js/lib/insertFragmentIntoContentState.js","name":"fragmentBlock","original":{"line":37,"column":10},"generated":{"line":1,"column":408}},{"source":"../node_modules/draft-js/lib/insertFragmentIntoContentState.js","name":"fragmentBlock","original":{"line":37,"column":10},"generated":{"line":1,"column":413}},{"source":"../node_modules/draft-js/lib/insertFragmentIntoContentState.js","name":"getData","original":{"line":37,"column":24},"generated":{"line":1,"column":415}},{"source":"../node_modules/draft-js/lib/insertFragmentIntoContentState.js","name":"contentState","original":{"line":40,"column":9},"generated":{"line":1,"column":427}},{"source":"../node_modules/draft-js/lib/insertFragmentIntoContentState.js","name":"contentState","original":{"line":40,"column":9},"generated":{"line":1,"column":434}},{"source":"../node_modules/draft-js/lib/insertFragmentIntoContentState.js","name":"merge","original":{"line":40,"column":22},"generated":{"line":1,"column":436}},{"source":"../node_modules/draft-js/lib/insertFragmentIntoContentState.js","original":{"line":40,"column":28},"generated":{"line":1,"column":442}},{"source":"../node_modules/draft-js/lib/insertFragmentIntoContentState.js","name":"blockMap","original":{"line":41,"column":14},"generated":{"line":1,"column":443}},{"source":"../node_modules/draft-js/lib/insertFragmentIntoContentState.js","name":"blockMap","original":{"line":41,"column":14},"generated":{"line":1,"column":452}},{"source":"../node_modules/draft-js/lib/insertFragmentIntoContentState.js","name":"set","original":{"line":41,"column":23},"generated":{"line":1,"column":454}},{"source":"../node_modules/draft-js/lib/insertFragmentIntoContentState.js","name":"targetKey","original":{"line":41,"column":27},"generated":{"line":1,"column":458}},{"source":"../node_modules/draft-js/lib/insertFragmentIntoContentState.js","name":"newBlock","original":{"line":41,"column":38},"generated":{"line":1,"column":460}},{"source":"../node_modules/draft-js/lib/insertFragmentIntoContentState.js","name":"selectionState","original":{"line":42,"column":21},"generated":{"line":1,"column":463}},{"source":"../node_modules/draft-js/lib/insertFragmentIntoContentState.js","name":"selectionState","original":{"line":42,"column":21},"generated":{"line":1,"column":479}},{"source":"../node_modules/draft-js/lib/insertFragmentIntoContentState.js","name":"selectionState","original":{"line":43,"column":20},"generated":{"line":1,"column":481}},{"source":"../node_modules/draft-js/lib/insertFragmentIntoContentState.js","name":"selectionState","original":{"line":43,"column":20},"generated":{"line":1,"column":496}},{"source":"../node_modules/draft-js/lib/insertFragmentIntoContentState.js","name":"merge","original":{"line":43,"column":35},"generated":{"line":1,"column":498}},{"source":"../node_modules/draft-js/lib/insertFragmentIntoContentState.js","original":{"line":43,"column":41},"generated":{"line":1,"column":504}},{"source":"../node_modules/draft-js/lib/insertFragmentIntoContentState.js","name":"finalKey","original":{"line":44,"column":17},"generated":{"line":1,"column":505}},{"source":"../node_modules/draft-js/lib/insertFragmentIntoContentState.js","name":"finalKey","original":{"line":44,"column":17},"generated":{"line":1,"column":515}},{"source":"../node_modules/draft-js/lib/insertFragmentIntoContentState.js","name":"finalOffset","original":{"line":45,"column":20},"generated":{"line":1,"column":517}},{"source":"../node_modules/draft-js/lib/insertFragmentIntoContentState.js","name":"finalOffset","original":{"line":45,"column":20},"generated":{"line":1,"column":530}},{"source":"../node_modules/draft-js/lib/insertFragmentIntoContentState.js","name":"finalKey","original":{"line":46,"column":16},"generated":{"line":1,"column":532}},{"source":"../node_modules/draft-js/lib/insertFragmentIntoContentState.js","name":"finalKey","original":{"line":46,"column":16},"generated":{"line":1,"column":541}},{"source":"../node_modules/draft-js/lib/insertFragmentIntoContentState.js","name":"finalOffset","original":{"line":47,"column":19},"generated":{"line":1,"column":543}},{"source":"../node_modules/draft-js/lib/insertFragmentIntoContentState.js","name":"finalOffset","original":{"line":47,"column":19},"generated":{"line":1,"column":555}},{"source":"../node_modules/draft-js/lib/insertFragmentIntoContentState.js","original":{"line":48,"column":18},"generated":{"line":1,"column":557}},{"source":"../node_modules/draft-js/lib/insertFragmentIntoContentState.js","original":{"line":48,"column":18},"generated":{"line":1,"column":569}},{"source":"../node_modules/draft-js/lib/insertFragmentIntoContentState.js","name":"updateHead","original":{"line":57,"column":4},"generated":{"line":1,"column":576}},{"source":"../node_modules/draft-js/lib/insertFragmentIntoContentState.js","original":{"line":57,"column":17},"generated":{"line":1,"column":578}},{"source":"../node_modules/draft-js/lib/insertFragmentIntoContentState.js","name":"block","original":{"line":57,"column":37},"generated":{"line":1,"column":587}},{"source":"../node_modules/draft-js/lib/insertFragmentIntoContentState.js","name":"targetOffset","original":{"line":57,"column":44},"generated":{"line":1,"column":589}},{"source":"../node_modules/draft-js/lib/insertFragmentIntoContentState.js","name":"fragment","original":{"line":57,"column":58},"generated":{"line":1,"column":591}},{"source":"../node_modules/draft-js/lib/insertFragmentIntoContentState.js","name":"text","original":{"line":58,"column":6},"generated":{"line":1,"column":594}},{"source":"../node_modules/draft-js/lib/insertFragmentIntoContentState.js","name":"text","original":{"line":58,"column":6},"generated":{"line":1,"column":598}},{"source":"../node_modules/draft-js/lib/insertFragmentIntoContentState.js","name":"block","original":{"line":58,"column":13},"generated":{"line":1,"column":600}},{"source":"../node_modules/draft-js/lib/insertFragmentIntoContentState.js","name":"getText","original":{"line":58,"column":19},"generated":{"line":1,"column":602}},{"source":"../node_modules/draft-js/lib/insertFragmentIntoContentState.js","name":"chars","original":{"line":59,"column":6},"generated":{"line":1,"column":612}},{"source":"../node_modules/draft-js/lib/insertFragmentIntoContentState.js","name":"block","original":{"line":59,"column":14},"generated":{"line":1,"column":614}},{"source":"../node_modules/draft-js/lib/insertFragmentIntoContentState.js","name":"getCharacterList","original":{"line":59,"column":20},"generated":{"line":1,"column":616}},{"source":"../node_modules/draft-js/lib/insertFragmentIntoContentState.js","name":"headText","original":{"line":62,"column":6},"generated":{"line":1,"column":635}},{"source":"../node_modules/draft-js/lib/insertFragmentIntoContentState.js","name":"text","original":{"line":62,"column":17},"generated":{"line":1,"column":637}},{"source":"../node_modules/draft-js/lib/insertFragmentIntoContentState.js","name":"slice","original":{"line":62,"column":22},"generated":{"line":1,"column":639}},{"source":"../node_modules/draft-js/lib/insertFragmentIntoContentState.js","original":{"line":62,"column":28},"generated":{"line":1,"column":645}},{"source":"../node_modules/draft-js/lib/insertFragmentIntoContentState.js","name":"targetOffset","original":{"line":62,"column":31},"generated":{"line":1,"column":647}},{"source":"../node_modules/draft-js/lib/insertFragmentIntoContentState.js","name":"headCharacters","original":{"line":63,"column":6},"generated":{"line":1,"column":650}},{"source":"../node_modules/draft-js/lib/insertFragmentIntoContentState.js","name":"chars","original":{"line":63,"column":23},"generated":{"line":1,"column":652}},{"source":"../node_modules/draft-js/lib/insertFragmentIntoContentState.js","name":"slice","original":{"line":63,"column":29},"generated":{"line":1,"column":654}},{"source":"../node_modules/draft-js/lib/insertFragmentIntoContentState.js","original":{"line":63,"column":35},"generated":{"line":1,"column":660}},{"source":"../node_modules/draft-js/lib/insertFragmentIntoContentState.js","name":"targetOffset","original":{"line":63,"column":38},"generated":{"line":1,"column":662}},{"source":"../node_modules/draft-js/lib/insertFragmentIntoContentState.js","name":"appendToHead","original":{"line":64,"column":6},"generated":{"line":1,"column":665}},{"source":"../node_modules/draft-js/lib/insertFragmentIntoContentState.js","name":"fragment","original":{"line":64,"column":21},"generated":{"line":1,"column":667}},{"source":"../node_modules/draft-js/lib/insertFragmentIntoContentState.js","name":"first","original":{"line":64,"column":30},"generated":{"line":1,"column":669}},{"source":"../node_modules/draft-js/lib/insertFragmentIntoContentState.js","name":"block","original":{"line":66,"column":9},"generated":{"line":1,"column":677}},{"source":"../node_modules/draft-js/lib/insertFragmentIntoContentState.js","name":"block","original":{"line":66,"column":9},"generated":{"line":1,"column":684}},{"source":"../node_modules/draft-js/lib/insertFragmentIntoContentState.js","name":"merge","original":{"line":66,"column":15},"generated":{"line":1,"column":686}},{"source":"../node_modules/draft-js/lib/insertFragmentIntoContentState.js","original":{"line":66,"column":21},"generated":{"line":1,"column":692}},{"source":"../node_modules/draft-js/lib/insertFragmentIntoContentState.js","name":"headText","original":{"line":67,"column":10},"generated":{"line":1,"column":693}},{"source":"../node_modules/draft-js/lib/insertFragmentIntoContentState.js","name":"headText","original":{"line":67,"column":10},"generated":{"line":1,"column":698}},{"source":"../node_modules/draft-js/lib/insertFragmentIntoContentState.js","name":"appendToHead","original":{"line":67,"column":21},"generated":{"line":1,"column":700}},{"source":"../node_modules/draft-js/lib/insertFragmentIntoContentState.js","name":"getText","original":{"line":67,"column":34},"generated":{"line":1,"column":702}},{"source":"../node_modules/draft-js/lib/insertFragmentIntoContentState.js","name":"headCharacters","original":{"line":68,"column":19},"generated":{"line":1,"column":712}},{"source":"../node_modules/draft-js/lib/insertFragmentIntoContentState.js","name":"headCharacters","original":{"line":68,"column":19},"generated":{"line":1,"column":726}},{"source":"../node_modules/draft-js/lib/insertFragmentIntoContentState.js","name":"concat","original":{"line":68,"column":34},"generated":{"line":1,"column":728}},{"source":"../node_modules/draft-js/lib/insertFragmentIntoContentState.js","name":"appendToHead","original":{"line":68,"column":41},"generated":{"line":1,"column":735}},{"source":"../node_modules/draft-js/lib/insertFragmentIntoContentState.js","name":"getCharacterList","original":{"line":68,"column":54},"generated":{"line":1,"column":737}},{"source":"../node_modules/draft-js/lib/insertFragmentIntoContentState.js","name":"headText","original":{"line":69,"column":10},"generated":{"line":1,"column":757}},{"source":"../node_modules/draft-js/lib/insertFragmentIntoContentState.js","name":"headText","original":{"line":69,"column":10},"generated":{"line":1,"column":762}},{"source":"../node_modules/draft-js/lib/insertFragmentIntoContentState.js","name":"block","original":{"line":69,"column":21},"generated":{"line":1,"column":764}},{"source":"../node_modules/draft-js/lib/insertFragmentIntoContentState.js","name":"getType","original":{"line":69,"column":27},"generated":{"line":1,"column":766}},{"source":"../node_modules/draft-js/lib/insertFragmentIntoContentState.js","name":"appendToHead","original":{"line":69,"column":39},"generated":{"line":1,"column":776}},{"source":"../node_modules/draft-js/lib/insertFragmentIntoContentState.js","name":"getType","original":{"line":69,"column":52},"generated":{"line":1,"column":778}},{"source":"../node_modules/draft-js/lib/insertFragmentIntoContentState.js","name":"appendToHead","original":{"line":70,"column":10},"generated":{"line":1,"column":788}},{"source":"../node_modules/draft-js/lib/insertFragmentIntoContentState.js","name":"appendToHead","original":{"line":70,"column":10},"generated":{"line":1,"column":793}},{"source":"../node_modules/draft-js/lib/insertFragmentIntoContentState.js","name":"getData","original":{"line":70,"column":23},"generated":{"line":1,"column":795}},{"source":"../node_modules/draft-js/lib/insertFragmentIntoContentState.js","name":"updateTail","original":{"line":78,"column":4},"generated":{"line":1,"column":808}},{"source":"../node_modules/draft-js/lib/insertFragmentIntoContentState.js","original":{"line":78,"column":17},"generated":{"line":1,"column":810}},{"source":"../node_modules/draft-js/lib/insertFragmentIntoContentState.js","name":"block","original":{"line":78,"column":37},"generated":{"line":1,"column":819}},{"source":"../node_modules/draft-js/lib/insertFragmentIntoContentState.js","name":"targetOffset","original":{"line":78,"column":44},"generated":{"line":1,"column":821}},{"source":"../node_modules/draft-js/lib/insertFragmentIntoContentState.js","name":"fragment","original":{"line":78,"column":58},"generated":{"line":1,"column":823}},{"source":"../node_modules/draft-js/lib/insertFragmentIntoContentState.js","name":"text","original":{"line":80,"column":6},"generated":{"line":1,"column":826}},{"source":"../node_modules/draft-js/lib/insertFragmentIntoContentState.js","name":"text","original":{"line":80,"column":6},"generated":{"line":1,"column":830}},{"source":"../node_modules/draft-js/lib/insertFragmentIntoContentState.js","name":"block","original":{"line":80,"column":13},"generated":{"line":1,"column":832}},{"source":"../node_modules/draft-js/lib/insertFragmentIntoContentState.js","name":"getText","original":{"line":80,"column":19},"generated":{"line":1,"column":834}},{"source":"../node_modules/draft-js/lib/insertFragmentIntoContentState.js","name":"chars","original":{"line":81,"column":6},"generated":{"line":1,"column":844}},{"source":"../node_modules/draft-js/lib/insertFragmentIntoContentState.js","name":"block","original":{"line":81,"column":14},"generated":{"line":1,"column":846}},{"source":"../node_modules/draft-js/lib/insertFragmentIntoContentState.js","name":"getCharacterList","original":{"line":81,"column":20},"generated":{"line":1,"column":848}},{"source":"../node_modules/draft-js/lib/insertFragmentIntoContentState.js","name":"blockSize","original":{"line":84,"column":6},"generated":{"line":1,"column":867}},{"source":"../node_modules/draft-js/lib/insertFragmentIntoContentState.js","name":"text","original":{"line":84,"column":18},"generated":{"line":1,"column":869}},{"source":"../node_modules/draft-js/lib/insertFragmentIntoContentState.js","name":"length","original":{"line":84,"column":23},"generated":{"line":1,"column":871}},{"source":"../node_modules/draft-js/lib/insertFragmentIntoContentState.js","name":"tailText","original":{"line":85,"column":6},"generated":{"line":1,"column":878}},{"source":"../node_modules/draft-js/lib/insertFragmentIntoContentState.js","name":"text","original":{"line":85,"column":17},"generated":{"line":1,"column":880}},{"source":"../node_modules/draft-js/lib/insertFragmentIntoContentState.js","name":"slice","original":{"line":85,"column":22},"generated":{"line":1,"column":882}},{"source":"../node_modules/draft-js/lib/insertFragmentIntoContentState.js","name":"targetOffset","original":{"line":85,"column":28},"generated":{"line":1,"column":888}},{"source":"../node_modules/draft-js/lib/insertFragmentIntoContentState.js","name":"blockSize","original":{"line":85,"column":42},"generated":{"line":1,"column":890}},{"source":"../node_modules/draft-js/lib/insertFragmentIntoContentState.js","name":"tailCharacters","original":{"line":86,"column":6},"generated":{"line":1,"column":893}},{"source":"../node_modules/draft-js/lib/insertFragmentIntoContentState.js","name":"chars","original":{"line":86,"column":23},"generated":{"line":1,"column":895}},{"source":"../node_modules/draft-js/lib/insertFragmentIntoContentState.js","name":"slice","original":{"line":86,"column":29},"generated":{"line":1,"column":897}},{"source":"../node_modules/draft-js/lib/insertFragmentIntoContentState.js","name":"targetOffset","original":{"line":86,"column":35},"generated":{"line":1,"column":903}},{"source":"../node_modules/draft-js/lib/insertFragmentIntoContentState.js","name":"blockSize","original":{"line":86,"column":49},"generated":{"line":1,"column":905}},{"source":"../node_modules/draft-js/lib/insertFragmentIntoContentState.js","name":"prependToTail","original":{"line":87,"column":6},"generated":{"line":1,"column":908}},{"source":"../node_modules/draft-js/lib/insertFragmentIntoContentState.js","name":"fragment","original":{"line":87,"column":22},"generated":{"line":1,"column":910}},{"source":"../node_modules/draft-js/lib/insertFragmentIntoContentState.js","name":"last","original":{"line":87,"column":31},"generated":{"line":1,"column":912}},{"source":"../node_modules/draft-js/lib/insertFragmentIntoContentState.js","name":"prependToTail","original":{"line":89,"column":9},"generated":{"line":1,"column":919}},{"source":"../node_modules/draft-js/lib/insertFragmentIntoContentState.js","name":"prependToTail","original":{"line":89,"column":9},"generated":{"line":1,"column":926}},{"source":"../node_modules/draft-js/lib/insertFragmentIntoContentState.js","name":"merge","original":{"line":89,"column":23},"generated":{"line":1,"column":928}},{"source":"../node_modules/draft-js/lib/insertFragmentIntoContentState.js","original":{"line":89,"column":29},"generated":{"line":1,"column":934}},{"source":"../node_modules/draft-js/lib/insertFragmentIntoContentState.js","name":"prependToTail","original":{"line":90,"column":10},"generated":{"line":1,"column":935}},{"source":"../node_modules/draft-js/lib/insertFragmentIntoContentState.js","name":"prependToTail","original":{"line":90,"column":10},"generated":{"line":1,"column":940}},{"source":"../node_modules/draft-js/lib/insertFragmentIntoContentState.js","name":"getText","original":{"line":90,"column":24},"generated":{"line":1,"column":942}},{"source":"../node_modules/draft-js/lib/insertFragmentIntoContentState.js","name":"tailText","original":{"line":90,"column":36},"generated":{"line":1,"column":952}},{"source":"../node_modules/draft-js/lib/insertFragmentIntoContentState.js","name":"prependToTail","original":{"line":91,"column":19},"generated":{"line":1,"column":954}},{"source":"../node_modules/draft-js/lib/insertFragmentIntoContentState.js","name":"prependToTail","original":{"line":91,"column":19},"generated":{"line":1,"column":968}},{"source":"../node_modules/draft-js/lib/insertFragmentIntoContentState.js","name":"getCharacterList","original":{"line":91,"column":33},"generated":{"line":1,"column":970}},{"source":"../node_modules/draft-js/lib/insertFragmentIntoContentState.js","name":"concat","original":{"line":91,"column":52},"generated":{"line":1,"column":989}},{"source":"../node_modules/draft-js/lib/insertFragmentIntoContentState.js","name":"tailCharacters","original":{"line":91,"column":59},"generated":{"line":1,"column":996}},{"source":"../node_modules/draft-js/lib/insertFragmentIntoContentState.js","name":"prependToTail","original":{"line":92,"column":10},"generated":{"line":1,"column":999}},{"source":"../node_modules/draft-js/lib/insertFragmentIntoContentState.js","name":"prependToTail","original":{"line":92,"column":10},"generated":{"line":1,"column":1004}},{"source":"../node_modules/draft-js/lib/insertFragmentIntoContentState.js","name":"getData","original":{"line":92,"column":24},"generated":{"line":1,"column":1006}},{"source":"../node_modules/draft-js/lib/insertFragmentIntoContentState.js","name":"getRootBlocks","original":{"line":96,"column":4},"generated":{"line":1,"column":1019}},{"source":"../node_modules/draft-js/lib/insertFragmentIntoContentState.js","original":{"line":96,"column":20},"generated":{"line":1,"column":1021}},{"source":"../node_modules/draft-js/lib/insertFragmentIntoContentState.js","name":"block","original":{"line":96,"column":43},"generated":{"line":1,"column":1030}},{"source":"../node_modules/draft-js/lib/insertFragmentIntoContentState.js","name":"blockMap","original":{"line":96,"column":50},"generated":{"line":1,"column":1032}},{"source":"../node_modules/draft-js/lib/insertFragmentIntoContentState.js","name":"headKey","original":{"line":97,"column":6},"generated":{"line":1,"column":1035}},{"source":"../node_modules/draft-js/lib/insertFragmentIntoContentState.js","name":"headKey","original":{"line":97,"column":6},"generated":{"line":1,"column":1039}},{"source":"../node_modules/draft-js/lib/insertFragmentIntoContentState.js","name":"block","original":{"line":97,"column":16},"generated":{"line":1,"column":1041}},{"source":"../node_modules/draft-js/lib/insertFragmentIntoContentState.js","name":"getKey","original":{"line":97,"column":22},"generated":{"line":1,"column":1043}},{"source":"../node_modules/draft-js/lib/insertFragmentIntoContentState.js","name":"rootBlock","original":{"line":98,"column":6},"generated":{"line":1,"column":1052}},{"source":"../node_modules/draft-js/lib/insertFragmentIntoContentState.js","name":"block","original":{"line":98,"column":18},"generated":{"line":1,"column":1054}},{"source":"../node_modules/draft-js/lib/insertFragmentIntoContentState.js","name":"rootBlocks","original":{"line":99,"column":6},"generated":{"line":1,"column":1056}},{"source":"../node_modules/draft-js/lib/insertFragmentIntoContentState.js","original":{"line":99,"column":19},"generated":{"line":1,"column":1058}},{"source":"../node_modules/draft-js/lib/insertFragmentIntoContentState.js","name":"rootBlock","original":{"line":109,"column":9},"generated":{"line":1,"column":1061}},{"source":"../node_modules/draft-js/lib/insertFragmentIntoContentState.js","name":"blockMap","original":{"line":105,"column":6},"generated":{"line":1,"column":1065}},{"source":"../node_modules/draft-js/lib/insertFragmentIntoContentState.js","name":"get","original":{"line":105,"column":15},"generated":{"line":1,"column":1067}},{"source":"../node_modules/draft-js/lib/insertFragmentIntoContentState.js","name":"headKey","original":{"line":105,"column":19},"generated":{"line":1,"column":1071}},{"source":"../node_modules/draft-js/lib/insertFragmentIntoContentState.js","name":"push","original":{"line":106,"column":15},"generated":{"line":1,"column":1075}},{"source":"../node_modules/draft-js/lib/insertFragmentIntoContentState.js","name":"push","original":{"line":106,"column":15},"generated":{"line":1,"column":1077}},{"source":"../node_modules/draft-js/lib/insertFragmentIntoContentState.js","name":"headKey","original":{"line":106,"column":20},"generated":{"line":1,"column":1082}},{"source":"../node_modules/draft-js/lib/insertFragmentIntoContentState.js","name":"rootBlock","original":{"line":109,"column":9},"generated":{"line":1,"column":1085}},{"source":"../node_modules/draft-js/lib/insertFragmentIntoContentState.js","name":"rootBlock","original":{"line":109,"column":22},"generated":{"line":1,"column":1088}},{"source":"../node_modules/draft-js/lib/insertFragmentIntoContentState.js","name":"getNextSiblingKey","original":{"line":109,"column":32},"generated":{"line":1,"column":1090}},{"source":"../node_modules/draft-js/lib/insertFragmentIntoContentState.js","original":{"line":109,"column":53},"generated":{"line":1,"column":1111}},{"source":"../node_modules/draft-js/lib/insertFragmentIntoContentState.js","name":"lastSiblingKey","original":{"line":110,"column":8},"generated":{"line":1,"column":1112}},{"source":"../node_modules/draft-js/lib/insertFragmentIntoContentState.js","name":"lastSiblingKey","original":{"line":110,"column":8},"generated":{"line":1,"column":1116}},{"source":"../node_modules/draft-js/lib/insertFragmentIntoContentState.js","name":"rootBlock","original":{"line":110,"column":25},"generated":{"line":1,"column":1118}},{"source":"../node_modules/draft-js/lib/insertFragmentIntoContentState.js","name":"getNextSiblingKey","original":{"line":110,"column":35},"generated":{"line":1,"column":1120}},{"source":"../node_modules/draft-js/lib/insertFragmentIntoContentState.js","original":{"line":112,"column":8},"generated":{"line":1,"column":1140}},{"source":"../node_modules/draft-js/lib/insertFragmentIntoContentState.js","name":"lastSiblingKey","original":{"line":112,"column":9},"generated":{"line":1,"column":1144}},{"source":"../node_modules/draft-js/lib/insertFragmentIntoContentState.js","original":{"line":113,"column":6},"generated":{"line":1,"column":1146}},{"source":"../node_modules/draft-js/lib/insertFragmentIntoContentState.js","name":"push","original":{"line":116,"column":15},"generated":{"line":1,"column":1152}},{"source":"../node_modules/draft-js/lib/insertFragmentIntoContentState.js","name":"push","original":{"line":116,"column":15},"generated":{"line":1,"column":1154}},{"source":"../node_modules/draft-js/lib/insertFragmentIntoContentState.js","name":"lastSiblingKey","original":{"line":116,"column":20},"generated":{"line":1,"column":1159}},{"source":"../node_modules/draft-js/lib/insertFragmentIntoContentState.js","name":"blockMap","original":{"line":117,"column":16},"generated":{"line":1,"column":1162}},{"source":"../node_modules/draft-js/lib/insertFragmentIntoContentState.js","name":"blockMap","original":{"line":117,"column":16},"generated":{"line":1,"column":1164}},{"source":"../node_modules/draft-js/lib/insertFragmentIntoContentState.js","name":"get","original":{"line":117,"column":25},"generated":{"line":1,"column":1166}},{"source":"../node_modules/draft-js/lib/insertFragmentIntoContentState.js","name":"lastSiblingKey","original":{"line":117,"column":29},"generated":{"line":1,"column":1170}},{"source":"../node_modules/draft-js/lib/insertFragmentIntoContentState.js","name":"rootBlocks","original":{"line":120,"column":9},"generated":{"line":1,"column":1173}},{"source":"../node_modules/draft-js/lib/insertFragmentIntoContentState.js","name":"rootBlocks","original":{"line":120,"column":9},"generated":{"line":1,"column":1180}},{"source":"../node_modules/draft-js/lib/insertFragmentIntoContentState.js","name":"updateBlockMapLinks","original":{"line":123,"column":4},"generated":{"line":1,"column":1183}},{"source":"../node_modules/draft-js/lib/insertFragmentIntoContentState.js","original":{"line":123,"column":26},"generated":{"line":1,"column":1185}},{"source":"../node_modules/draft-js/lib/insertFragmentIntoContentState.js","name":"blockMap","original":{"line":123,"column":55},"generated":{"line":1,"column":1194}},{"source":"../node_modules/draft-js/lib/insertFragmentIntoContentState.js","name":"originalBlockMap","original":{"line":123,"column":65},"generated":{"line":1,"column":1196}},{"source":"../node_modules/draft-js/lib/insertFragmentIntoContentState.js","name":"targetBlock","original":{"line":123,"column":83},"generated":{"line":1,"column":1198}},{"source":"../node_modules/draft-js/lib/insertFragmentIntoContentState.js","name":"fragmentHeadBlock","original":{"line":123,"column":96},"generated":{"line":1,"column":1200}},{"source":"../node_modules/draft-js/lib/insertFragmentIntoContentState.js","name":"blockMap","original":{"line":124,"column":9},"generated":{"line":1,"column":1203}},{"source":"../node_modules/draft-js/lib/insertFragmentIntoContentState.js","name":"blockMap","original":{"line":124,"column":9},"generated":{"line":1,"column":1210}},{"source":"../node_modules/draft-js/lib/insertFragmentIntoContentState.js","name":"withMutations","original":{"line":124,"column":18},"generated":{"line":1,"column":1212}},{"source":"../node_modules/draft-js/lib/insertFragmentIntoContentState.js","original":{"line":124,"column":32},"generated":{"line":1,"column":1226}},{"source":"../node_modules/draft-js/lib/insertFragmentIntoContentState.js","name":"blockMapState","original":{"line":124,"column":42},"generated":{"line":1,"column":1235}},{"source":"../node_modules/draft-js/lib/insertFragmentIntoContentState.js","name":"targetKey","original":{"line":125,"column":8},"generated":{"line":1,"column":1238}},{"source":"../node_modules/draft-js/lib/insertFragmentIntoContentState.js","name":"targetKey","original":{"line":125,"column":8},"generated":{"line":1,"column":1242}},{"source":"../node_modules/draft-js/lib/insertFragmentIntoContentState.js","name":"targetBlock","original":{"line":125,"column":20},"generated":{"line":1,"column":1244}},{"source":"../node_modules/draft-js/lib/insertFragmentIntoContentState.js","name":"getKey","original":{"line":125,"column":32},"generated":{"line":1,"column":1246}},{"source":"../node_modules/draft-js/lib/insertFragmentIntoContentState.js","name":"headKey","original":{"line":126,"column":8},"generated":{"line":1,"column":1255}},{"source":"../node_modules/draft-js/lib/insertFragmentIntoContentState.js","name":"fragmentHeadBlock","original":{"line":126,"column":18},"generated":{"line":1,"column":1257}},{"source":"../node_modules/draft-js/lib/insertFragmentIntoContentState.js","name":"getKey","original":{"line":126,"column":36},"generated":{"line":1,"column":1259}},{"source":"../node_modules/draft-js/lib/insertFragmentIntoContentState.js","name":"targetNextKey","original":{"line":127,"column":8},"generated":{"line":1,"column":1268}},{"source":"../node_modules/draft-js/lib/insertFragmentIntoContentState.js","name":"targetBlock","original":{"line":127,"column":24},"generated":{"line":1,"column":1270}},{"source":"../node_modules/draft-js/lib/insertFragmentIntoContentState.js","name":"getNextSiblingKey","original":{"line":127,"column":36},"generated":{"line":1,"column":1272}},{"source":"../node_modules/draft-js/lib/insertFragmentIntoContentState.js","name":"targetParentKey","original":{"line":128,"column":8},"generated":{"line":1,"column":1292}},{"source":"../node_modules/draft-js/lib/insertFragmentIntoContentState.js","name":"targetBlock","original":{"line":128,"column":26},"generated":{"line":1,"column":1294}},{"source":"../node_modules/draft-js/lib/insertFragmentIntoContentState.js","name":"getParentKey","original":{"line":128,"column":38},"generated":{"line":1,"column":1296}},{"source":"../node_modules/draft-js/lib/insertFragmentIntoContentState.js","name":"fragmentRootBlocks","original":{"line":129,"column":8},"generated":{"line":1,"column":1311}},{"source":"../node_modules/draft-js/lib/insertFragmentIntoContentState.js","name":"getRootBlocks","original":{"line":129,"column":29},"generated":{"line":1,"column":1313}},{"source":"../node_modules/draft-js/lib/insertFragmentIntoContentState.js","name":"fragmentHeadBlock","original":{"line":129,"column":43},"generated":{"line":1,"column":1315}},{"source":"../node_modules/draft-js/lib/insertFragmentIntoContentState.js","name":"blockMap","original":{"line":129,"column":62},"generated":{"line":1,"column":1317}},{"source":"../node_modules/draft-js/lib/insertFragmentIntoContentState.js","name":"lastRootFragmentBlockKey","original":{"line":130,"column":8},"generated":{"line":1,"column":1320}},{"source":"../node_modules/draft-js/lib/insertFragmentIntoContentState.js","name":"fragmentRootBlocks","original":{"line":130,"column":35},"generated":{"line":1,"column":1322}},{"source":"../node_modules/draft-js/lib/insertFragmentIntoContentState.js","name":"fragmentRootBlocks","original":{"line":130,"column":54},"generated":{"line":1,"column":1324}},{"source":"../node_modules/draft-js/lib/insertFragmentIntoContentState.js","name":"length","original":{"line":130,"column":73},"generated":{"line":1,"column":1326}},{"source":"../node_modules/draft-js/lib/insertFragmentIntoContentState.js","original":{"line":130,"column":82},"generated":{"line":1,"column":1333}},{"source":"../node_modules/draft-js/lib/insertFragmentIntoContentState.js","name":"targetParentKey","original":{"line":156,"column":8},"generated":{"line":1,"column":1336}},{"source":"../node_modules/draft-js/lib/insertFragmentIntoContentState.js","name":"blockMapState","original":{"line":132,"column":8},"generated":{"line":1,"column":1339}},{"source":"../node_modules/draft-js/lib/insertFragmentIntoContentState.js","name":"get","original":{"line":132,"column":22},"generated":{"line":1,"column":1341}},{"source":"../node_modules/draft-js/lib/insertFragmentIntoContentState.js","name":"headKey","original":{"line":132,"column":26},"generated":{"line":1,"column":1345}},{"source":"../node_modules/draft-js/lib/insertFragmentIntoContentState.js","name":"setIn","original":{"line":134,"column":20},"generated":{"line":1,"column":1349}},{"source":"../node_modules/draft-js/lib/insertFragmentIntoContentState.js","name":"setIn","original":{"line":134,"column":20},"generated":{"line":1,"column":1351}},{"source":"../node_modules/draft-js/lib/insertFragmentIntoContentState.js","original":{"line":134,"column":26},"generated":{"line":1,"column":1357}},{"source":"../node_modules/draft-js/lib/insertFragmentIntoContentState.js","name":"targetKey","original":{"line":134,"column":27},"generated":{"line":1,"column":1358}},{"source":"../node_modules/draft-js/lib/insertFragmentIntoContentState.js","original":{"line":134,"column":38},"generated":{"line":1,"column":1360}},{"source":"../node_modules/draft-js/lib/insertFragmentIntoContentState.js","name":"headKey","original":{"line":134,"column":54},"generated":{"line":1,"column":1375}},{"source":"../node_modules/draft-js/lib/insertFragmentIntoContentState.js","name":"setIn","original":{"line":135,"column":20},"generated":{"line":1,"column":1378}},{"source":"../node_modules/draft-js/lib/insertFragmentIntoContentState.js","name":"setIn","original":{"line":135,"column":20},"generated":{"line":1,"column":1380}},{"source":"../node_modules/draft-js/lib/insertFragmentIntoContentState.js","original":{"line":135,"column":26},"generated":{"line":1,"column":1386}},{"source":"../node_modules/draft-js/lib/insertFragmentIntoContentState.js","name":"headKey","original":{"line":135,"column":27},"generated":{"line":1,"column":1387}},{"source":"../node_modules/draft-js/lib/insertFragmentIntoContentState.js","original":{"line":135,"column":36},"generated":{"line":1,"column":1389}},{"source":"../node_modules/draft-js/lib/insertFragmentIntoContentState.js","name":"targetKey","original":{"line":135,"column":52},"generated":{"line":1,"column":1404}},{"source":"../node_modules/draft-js/lib/insertFragmentIntoContentState.js","name":"setIn","original":{"line":138,"column":20},"generated":{"line":1,"column":1409}},{"source":"../node_modules/draft-js/lib/insertFragmentIntoContentState.js","name":"setIn","original":{"line":138,"column":20},"generated":{"line":1,"column":1411}},{"source":"../node_modules/draft-js/lib/insertFragmentIntoContentState.js","original":{"line":138,"column":26},"generated":{"line":1,"column":1417}},{"source":"../node_modules/draft-js/lib/insertFragmentIntoContentState.js","name":"targetKey","original":{"line":138,"column":27},"generated":{"line":1,"column":1418}},{"source":"../node_modules/draft-js/lib/insertFragmentIntoContentState.js","original":{"line":138,"column":38},"generated":{"line":1,"column":1420}},{"source":"../node_modules/draft-js/lib/insertFragmentIntoContentState.js","name":"fragmentHeadBlock","original":{"line":138,"column":54},"generated":{"line":1,"column":1435}},{"source":"../node_modules/draft-js/lib/insertFragmentIntoContentState.js","name":"getNextSiblingKey","original":{"line":138,"column":72},"generated":{"line":1,"column":1437}},{"source":"../node_modules/draft-js/lib/insertFragmentIntoContentState.js","name":"setIn","original":{"line":139,"column":20},"generated":{"line":1,"column":1458}},{"source":"../node_modules/draft-js/lib/insertFragmentIntoContentState.js","name":"setIn","original":{"line":139,"column":20},"generated":{"line":1,"column":1460}},{"source":"../node_modules/draft-js/lib/insertFragmentIntoContentState.js","original":{"line":139,"column":26},"generated":{"line":1,"column":1466}},{"source":"../node_modules/draft-js/lib/insertFragmentIntoContentState.js","name":"fragmentHeadBlock","original":{"line":139,"column":27},"generated":{"line":1,"column":1467}},{"source":"../node_modules/draft-js/lib/insertFragmentIntoContentState.js","name":"getNextSiblingKey","original":{"line":139,"column":45},"generated":{"line":1,"column":1469}},{"source":"../node_modules/draft-js/lib/insertFragmentIntoContentState.js","original":{"line":139,"column":66},"generated":{"line":1,"column":1489}},{"source":"../node_modules/draft-js/lib/insertFragmentIntoContentState.js","name":"targetKey","original":{"line":139,"column":82},"generated":{"line":1,"column":1504}},{"source":"../node_modules/draft-js/lib/insertFragmentIntoContentState.js","name":"setIn","original":{"line":143,"column":18},"generated":{"line":1,"column":1508}},{"source":"../node_modules/draft-js/lib/insertFragmentIntoContentState.js","name":"setIn","original":{"line":143,"column":18},"generated":{"line":1,"column":1510}},{"source":"../node_modules/draft-js/lib/insertFragmentIntoContentState.js","original":{"line":143,"column":24},"generated":{"line":1,"column":1516}},{"source":"../node_modules/draft-js/lib/insertFragmentIntoContentState.js","name":"lastRootFragmentBlockKey","original":{"line":143,"column":25},"generated":{"line":1,"column":1517}},{"source":"../node_modules/draft-js/lib/insertFragmentIntoContentState.js","original":{"line":143,"column":51},"generated":{"line":1,"column":1519}},{"source":"../node_modules/draft-js/lib/insertFragmentIntoContentState.js","name":"targetNextKey","original":{"line":143,"column":67},"generated":{"line":1,"column":1534}},{"source":"../node_modules/draft-js/lib/insertFragmentIntoContentState.js","name":"targetNextKey","original":{"line":146,"column":8},"generated":{"line":1,"column":1537}},{"source":"../node_modules/draft-js/lib/insertFragmentIntoContentState.js","name":"setIn","original":{"line":147,"column":20},"generated":{"line":1,"column":1540}},{"source":"../node_modules/draft-js/lib/insertFragmentIntoContentState.js","name":"setIn","original":{"line":147,"column":20},"generated":{"line":1,"column":1542}},{"source":"../node_modules/draft-js/lib/insertFragmentIntoContentState.js","original":{"line":147,"column":26},"generated":{"line":1,"column":1548}},{"source":"../node_modules/draft-js/lib/insertFragmentIntoContentState.js","name":"targetNextKey","original":{"line":147,"column":27},"generated":{"line":1,"column":1549}},{"source":"../node_modules/draft-js/lib/insertFragmentIntoContentState.js","original":{"line":147,"column":42},"generated":{"line":1,"column":1551}},{"source":"../node_modules/draft-js/lib/insertFragmentIntoContentState.js","name":"lastRootFragmentBlockKey","original":{"line":147,"column":58},"generated":{"line":1,"column":1566}},{"source":"../node_modules/draft-js/lib/insertFragmentIntoContentState.js","name":"forEach","original":{"line":151,"column":23},"generated":{"line":1,"column":1569}},{"source":"../node_modules/draft-js/lib/insertFragmentIntoContentState.js","name":"forEach","original":{"line":151,"column":23},"generated":{"line":1,"column":1571}},{"source":"../node_modules/draft-js/lib/insertFragmentIntoContentState.js","original":{"line":151,"column":31},"generated":{"line":1,"column":1579}},{"source":"../node_modules/draft-js/lib/insertFragmentIntoContentState.js","name":"blockKey","original":{"line":151,"column":41},"generated":{"line":1,"column":1588}},{"source":"../node_modules/draft-js/lib/insertFragmentIntoContentState.js","name":"blockMapState","original":{"line":152,"column":13},"generated":{"line":1,"column":1591}},{"source":"../node_modules/draft-js/lib/insertFragmentIntoContentState.js","name":"blockMapState","original":{"line":152,"column":13},"generated":{"line":1,"column":1598}},{"source":"../node_modules/draft-js/lib/insertFragmentIntoContentState.js","name":"setIn","original":{"line":152,"column":27},"generated":{"line":1,"column":1600}},{"source":"../node_modules/draft-js/lib/insertFragmentIntoContentState.js","original":{"line":152,"column":33},"generated":{"line":1,"column":1606}},{"source":"../node_modules/draft-js/lib/insertFragmentIntoContentState.js","name":"blockKey","original":{"line":152,"column":34},"generated":{"line":1,"column":1607}},{"source":"../node_modules/draft-js/lib/insertFragmentIntoContentState.js","original":{"line":152,"column":44},"generated":{"line":1,"column":1609}},{"source":"../node_modules/draft-js/lib/insertFragmentIntoContentState.js","name":"targetParentKey","original":{"line":152,"column":55},"generated":{"line":1,"column":1619}},{"source":"../node_modules/draft-js/lib/insertFragmentIntoContentState.js","name":"targetParentKey","original":{"line":156,"column":8},"generated":{"line":1,"column":1624}},{"source":"../node_modules/draft-js/lib/insertFragmentIntoContentState.js","original":{"line":156,"column":25},"generated":{"line":1,"column":1626}},{"source":"../node_modules/draft-js/lib/insertFragmentIntoContentState.js","name":"targetParent","original":{"line":157,"column":10},"generated":{"line":1,"column":1627}},{"source":"../node_modules/draft-js/lib/insertFragmentIntoContentState.js","name":"originalTargetParentChildKeys","original":{"line":158,"column":10},"generated":{"line":1,"column":1631}},{"source":"../node_modules/draft-js/lib/insertFragmentIntoContentState.js","name":"blockMap","original":{"line":157,"column":25},"generated":{"line":1,"column":1633}},{"source":"../node_modules/draft-js/lib/insertFragmentIntoContentState.js","name":"get","original":{"line":157,"column":34},"generated":{"line":1,"column":1635}},{"source":"../node_modules/draft-js/lib/insertFragmentIntoContentState.js","name":"targetParentKey","original":{"line":157,"column":38},"generated":{"line":1,"column":1639}},{"source":"../node_modules/draft-js/lib/insertFragmentIntoContentState.js","name":"getChildKeys","original":{"line":158,"column":55},"generated":{"line":1,"column":1642}},{"source":"../node_modules/draft-js/lib/insertFragmentIntoContentState.js","name":"insertionIndex","original":{"line":161,"column":10},"generated":{"line":1,"column":1657}},{"source":"../node_modules/draft-js/lib/insertFragmentIntoContentState.js","name":"originalTargetParentChildKeys","original":{"line":160,"column":29},"generated":{"line":1,"column":1659}},{"source":"../node_modules/draft-js/lib/insertFragmentIntoContentState.js","name":"indexOf","original":{"line":160,"column":59},"generated":{"line":1,"column":1661}},{"source":"../node_modules/draft-js/lib/insertFragmentIntoContentState.js","name":"targetKey","original":{"line":160,"column":67},"generated":{"line":1,"column":1669}},{"source":"../node_modules/draft-js/lib/insertFragmentIntoContentState.js","original":{"line":161,"column":46},"generated":{"line":1,"column":1672}},{"source":"../node_modules/draft-js/lib/insertFragmentIntoContentState.js","name":"newChildrenKeysArray","original":{"line":163,"column":10},"generated":{"line":1,"column":1674}},{"source":"../node_modules/draft-js/lib/insertFragmentIntoContentState.js","name":"originalTargetParentChildKeys","original":{"line":163,"column":33},"generated":{"line":1,"column":1676}},{"source":"../node_modules/draft-js/lib/insertFragmentIntoContentState.js","name":"toArray","original":{"line":163,"column":63},"generated":{"line":1,"column":1678}},{"source":"../node_modules/draft-js/lib/insertFragmentIntoContentState.js","name":"splice","original":{"line":166,"column":27},"generated":{"line":1,"column":1688}},{"source":"../node_modules/draft-js/lib/insertFragmentIntoContentState.js","name":"splice","original":{"line":166,"column":27},"generated":{"line":1,"column":1690}},{"source":"../node_modules/draft-js/lib/insertFragmentIntoContentState.js","name":"apply","original":{"line":166,"column":34},"generated":{"line":1,"column":1697}},{"source":"../node_modules/draft-js/lib/insertFragmentIntoContentState.js","name":"newChildrenKeysArray","original":{"line":166,"column":40},"generated":{"line":1,"column":1703}},{"source":"../node_modules/draft-js/lib/insertFragmentIntoContentState.js","original":{"line":166,"column":62},"generated":{"line":1,"column":1705}},{"source":"../node_modules/draft-js/lib/insertFragmentIntoContentState.js","name":"insertionIndex","original":{"line":166,"column":63},"generated":{"line":1,"column":1706}},{"source":"../node_modules/draft-js/lib/insertFragmentIntoContentState.js","original":{"line":166,"column":79},"generated":{"line":1,"column":1708}},{"source":"../node_modules/draft-js/lib/insertFragmentIntoContentState.js","name":"concat","original":{"line":166,"column":82},"generated":{"line":1,"column":1711}},{"source":"../node_modules/draft-js/lib/insertFragmentIntoContentState.js","name":"fragmentRootBlocks","original":{"line":166,"column":89},"generated":{"line":1,"column":1718}},{"source":"../node_modules/draft-js/lib/insertFragmentIntoContentState.js","name":"setIn","original":{"line":168,"column":20},"generated":{"line":1,"column":1722}},{"source":"../node_modules/draft-js/lib/insertFragmentIntoContentState.js","name":"setIn","original":{"line":168,"column":20},"generated":{"line":1,"column":1724}},{"source":"../node_modules/draft-js/lib/insertFragmentIntoContentState.js","original":{"line":168,"column":26},"generated":{"line":1,"column":1730}},{"source":"../node_modules/draft-js/lib/insertFragmentIntoContentState.js","name":"targetParentKey","original":{"line":168,"column":27},"generated":{"line":1,"column":1731}},{"source":"../node_modules/draft-js/lib/insertFragmentIntoContentState.js","original":{"line":168,"column":44},"generated":{"line":1,"column":1733}},{"source":"../node_modules/draft-js/lib/insertFragmentIntoContentState.js","name":"List","original":{"line":168,"column":57},"generated":{"line":1,"column":1745}},{"source":"../node_modules/draft-js/lib/insertFragmentIntoContentState.js","name":"newChildrenKeysArray","original":{"line":168,"column":62},"generated":{"line":1,"column":1747}},{"source":"../node_modules/draft-js/lib/insertFragmentIntoContentState.js","name":"insertFragment","original":{"line":173,"column":4},"generated":{"line":1,"column":1755}},{"source":"../node_modules/draft-js/lib/insertFragmentIntoContentState.js","original":{"line":173,"column":21},"generated":{"line":1,"column":1757}},{"source":"../node_modules/draft-js/lib/insertFragmentIntoContentState.js","name":"contentState","original":{"line":173,"column":45},"generated":{"line":1,"column":1766}},{"source":"../node_modules/draft-js/lib/insertFragmentIntoContentState.js","name":"selectionState","original":{"line":173,"column":59},"generated":{"line":1,"column":1768}},{"source":"../node_modules/draft-js/lib/insertFragmentIntoContentState.js","name":"blockMap","original":{"line":173,"column":75},"generated":{"line":1,"column":1770}},{"source":"../node_modules/draft-js/lib/insertFragmentIntoContentState.js","name":"fragment","original":{"line":173,"column":85},"generated":{"line":1,"column":1772}},{"source":"../node_modules/draft-js/lib/insertFragmentIntoContentState.js","name":"targetKey","original":{"line":173,"column":95},"generated":{"line":1,"column":1774}},{"source":"../node_modules/draft-js/lib/insertFragmentIntoContentState.js","name":"targetOffset","original":{"line":173,"column":106},"generated":{"line":1,"column":1776}},{"source":"../node_modules/draft-js/lib/insertFragmentIntoContentState.js","name":"isTreeBasedBlockMap","original":{"line":174,"column":6},"generated":{"line":1,"column":1779}},{"source":"../node_modules/draft-js/lib/insertFragmentIntoContentState.js","name":"isTreeBasedBlockMap","original":{"line":174,"column":6},"generated":{"line":1,"column":1783}},{"source":"../node_modules/draft-js/lib/insertFragmentIntoContentState.js","name":"blockMap","original":{"line":174,"column":28},"generated":{"line":1,"column":1785}},{"source":"../node_modules/draft-js/lib/insertFragmentIntoContentState.js","name":"first","original":{"line":174,"column":37},"generated":{"line":1,"column":1787}},{"source":"../node_modules/draft-js/lib/insertFragmentIntoContentState.js","name":"ContentBlockNode","original":{"line":174,"column":56},"generated":{"line":1,"column":1805}},{"source":"../node_modules/draft-js/lib/insertFragmentIntoContentState.js","name":"newBlockArr","original":{"line":175,"column":6},"generated":{"line":1,"column":1807}},{"source":"../node_modules/draft-js/lib/insertFragmentIntoContentState.js","original":{"line":175,"column":20},"generated":{"line":1,"column":1809}},{"source":"../node_modules/draft-js/lib/insertFragmentIntoContentState.js","name":"fragmentSize","original":{"line":176,"column":6},"generated":{"line":1,"column":1812}},{"source":"../node_modules/draft-js/lib/insertFragmentIntoContentState.js","name":"fragment","original":{"line":176,"column":21},"generated":{"line":1,"column":1814}},{"source":"../node_modules/draft-js/lib/insertFragmentIntoContentState.js","name":"size","original":{"line":176,"column":30},"generated":{"line":1,"column":1816}},{"source":"../node_modules/draft-js/lib/insertFragmentIntoContentState.js","name":"target","original":{"line":177,"column":6},"generated":{"line":1,"column":1821}},{"source":"../node_modules/draft-js/lib/insertFragmentIntoContentState.js","name":"blockMap","original":{"line":177,"column":15},"generated":{"line":1,"column":1823}},{"source":"../node_modules/draft-js/lib/insertFragmentIntoContentState.js","name":"get","original":{"line":177,"column":24},"generated":{"line":1,"column":1825}},{"source":"../node_modules/draft-js/lib/insertFragmentIntoContentState.js","name":"targetKey","original":{"line":177,"column":28},"generated":{"line":1,"column":1829}},{"source":"../node_modules/draft-js/lib/insertFragmentIntoContentState.js","name":"head","original":{"line":178,"column":6},"generated":{"line":1,"column":1832}},{"source":"../node_modules/draft-js/lib/insertFragmentIntoContentState.js","name":"fragment","original":{"line":178,"column":13},"generated":{"line":1,"column":1834}},{"source":"../node_modules/draft-js/lib/insertFragmentIntoContentState.js","name":"first","original":{"line":178,"column":22},"generated":{"line":1,"column":1836}},{"source":"../node_modules/draft-js/lib/insertFragmentIntoContentState.js","name":"tail","original":{"line":179,"column":6},"generated":{"line":1,"column":1844}},{"source":"../node_modules/draft-js/lib/insertFragmentIntoContentState.js","name":"fragment","original":{"line":179,"column":13},"generated":{"line":1,"column":1846}},{"source":"../node_modules/draft-js/lib/insertFragmentIntoContentState.js","name":"last","original":{"line":179,"column":22},"generated":{"line":1,"column":1848}},{"source":"../node_modules/draft-js/lib/insertFragmentIntoContentState.js","name":"finalOffset","original":{"line":180,"column":6},"generated":{"line":1,"column":1855}},{"source":"../node_modules/draft-js/lib/insertFragmentIntoContentState.js","name":"tail","original":{"line":180,"column":20},"generated":{"line":1,"column":1857}},{"source":"../node_modules/draft-js/lib/insertFragmentIntoContentState.js","name":"getLength","original":{"line":180,"column":25},"generated":{"line":1,"column":1859}},{"source":"../node_modules/draft-js/lib/insertFragmentIntoContentState.js","name":"finalKey","original":{"line":181,"column":6},"generated":{"line":1,"column":1871}},{"source":"../node_modules/draft-js/lib/insertFragmentIntoContentState.js","name":"tail","original":{"line":181,"column":17},"generated":{"line":1,"column":1873}},{"source":"../node_modules/draft-js/lib/insertFragmentIntoContentState.js","name":"getKey","original":{"line":181,"column":22},"generated":{"line":1,"column":1875}},{"source":"../node_modules/draft-js/lib/insertFragmentIntoContentState.js","name":"shouldNotUpdateFromFragmentBlock","original":{"line":182,"column":6},"generated":{"line":1,"column":1884}},{"source":"../node_modules/draft-js/lib/insertFragmentIntoContentState.js","name":"isTreeBasedBlockMap","original":{"line":182,"column":41},"generated":{"line":1,"column":1886}},{"source":"../node_modules/draft-js/lib/insertFragmentIntoContentState.js","name":"target","original":{"line":182,"column":66},"generated":{"line":1,"column":1891}},{"source":"../node_modules/draft-js/lib/insertFragmentIntoContentState.js","name":"getChildKeys","original":{"line":182,"column":73},"generated":{"line":1,"column":1893}},{"source":"../node_modules/draft-js/lib/insertFragmentIntoContentState.js","name":"isEmpty","original":{"line":182,"column":88},"generated":{"line":1,"column":1908}},{"source":"../node_modules/draft-js/lib/insertFragmentIntoContentState.js","name":"head","original":{"line":182,"column":102},"generated":{"line":1,"column":1920}},{"source":"../node_modules/draft-js/lib/insertFragmentIntoContentState.js","name":"getChildKeys","original":{"line":182,"column":107},"generated":{"line":1,"column":1922}},{"source":"../node_modules/draft-js/lib/insertFragmentIntoContentState.js","name":"isEmpty","original":{"line":182,"column":122},"generated":{"line":1,"column":1937}},{"source":"../node_modules/draft-js/lib/insertFragmentIntoContentState.js","name":"forEach","original":{"line":184,"column":11},"generated":{"line":1,"column":1948}},{"source":"../node_modules/draft-js/lib/insertFragmentIntoContentState.js","name":"forEach","original":{"line":184,"column":11},"generated":{"line":1,"column":1950}},{"source":"../node_modules/draft-js/lib/insertFragmentIntoContentState.js","original":{"line":184,"column":19},"generated":{"line":1,"column":1958}},{"source":"../node_modules/draft-js/lib/insertFragmentIntoContentState.js","name":"block","original":{"line":184,"column":29},"generated":{"line":1,"column":1967}},{"source":"../node_modules/draft-js/lib/insertFragmentIntoContentState.js","name":"blockKey","original":{"line":184,"column":36},"generated":{"line":1,"column":1969}},{"source":"../node_modules/draft-js/lib/insertFragmentIntoContentState.js","name":"blockKey","original":{"line":185,"column":8},"generated":{"line":1,"column":1972}},{"source":"../node_modules/draft-js/lib/insertFragmentIntoContentState.js","name":"targetKey","original":{"line":185,"column":21},"generated":{"line":1,"column":1976}},{"source":"../node_modules/draft-js/lib/insertFragmentIntoContentState.js","name":"shouldNotUpdateFromFragmentBlock","original":{"line":190,"column":8},"generated":{"line":1,"column":1979}},{"source":"../node_modules/draft-js/lib/insertFragmentIntoContentState.js","name":"push","original":{"line":191,"column":18},"generated":{"line":1,"column":1981}},{"source":"../node_modules/draft-js/lib/insertFragmentIntoContentState.js","name":"push","original":{"line":191,"column":18},"generated":{"line":1,"column":1983}},{"source":"../node_modules/draft-js/lib/insertFragmentIntoContentState.js","name":"block","original":{"line":191,"column":23},"generated":{"line":1,"column":1988}},{"source":"../node_modules/draft-js/lib/insertFragmentIntoContentState.js","name":"push","original":{"line":193,"column":18},"generated":{"line":1,"column":1991}},{"source":"../node_modules/draft-js/lib/insertFragmentIntoContentState.js","name":"push","original":{"line":193,"column":18},"generated":{"line":1,"column":1993}},{"source":"../node_modules/draft-js/lib/insertFragmentIntoContentState.js","name":"updateHead","original":{"line":193,"column":23},"generated":{"line":1,"column":1998}},{"source":"../node_modules/draft-js/lib/insertFragmentIntoContentState.js","name":"block","original":{"line":193,"column":34},"generated":{"line":1,"column":2000}},{"source":"../node_modules/draft-js/lib/insertFragmentIntoContentState.js","name":"targetOffset","original":{"line":193,"column":41},"generated":{"line":1,"column":2002}},{"source":"../node_modules/draft-js/lib/insertFragmentIntoContentState.js","name":"fragment","original":{"line":193,"column":55},"generated":{"line":1,"column":2004}},{"source":"../node_modules/draft-js/lib/insertFragmentIntoContentState.js","name":"fragment","original":{"line":197,"column":4},"generated":{"line":1,"column":2008}},{"source":"../node_modules/draft-js/lib/insertFragmentIntoContentState.js","name":"slice","original":{"line":201,"column":5},"generated":{"line":1,"column":2010}},{"source":"../node_modules/draft-js/lib/insertFragmentIntoContentState.js","name":"shouldNotUpdateFromFragmentBlock","original":{"line":201,"column":11},"generated":{"line":1,"column":2016}},{"source":"../node_modules/draft-js/lib/insertFragmentIntoContentState.js","original":{"line":201,"column":46},"generated":{"line":1,"column":2018}},{"source":"../node_modules/draft-js/lib/insertFragmentIntoContentState.js","original":{"line":201,"column":50},"generated":{"line":1,"column":2020}},{"source":"../node_modules/draft-js/lib/insertFragmentIntoContentState.js","name":"fragmentSize","original":{"line":201,"column":53},"generated":{"line":1,"column":2022}},{"source":"../node_modules/draft-js/lib/insertFragmentIntoContentState.js","original":{"line":201,"column":68},"generated":{"line":1,"column":2024}},{"source":"../node_modules/draft-js/lib/insertFragmentIntoContentState.js","name":"forEach","original":{"line":201,"column":71},"generated":{"line":1,"column":2027}},{"source":"../node_modules/draft-js/lib/insertFragmentIntoContentState.js","original":{"line":201,"column":79},"generated":{"line":1,"column":2035}},{"source":"../node_modules/draft-js/lib/insertFragmentIntoContentState.js","name":"fragmentBlock","original":{"line":201,"column":89},"generated":{"line":1,"column":2044}},{"source":"../node_modules/draft-js/lib/insertFragmentIntoContentState.js","name":"newBlockArr","original":{"line":202,"column":13},"generated":{"line":1,"column":2047}},{"source":"../node_modules/draft-js/lib/insertFragmentIntoContentState.js","name":"newBlockArr","original":{"line":202,"column":13},"generated":{"line":1,"column":2054}},{"source":"../node_modules/draft-js/lib/insertFragmentIntoContentState.js","name":"push","original":{"line":202,"column":25},"generated":{"line":1,"column":2056}},{"source":"../node_modules/draft-js/lib/insertFragmentIntoContentState.js","name":"fragmentBlock","original":{"line":202,"column":30},"generated":{"line":1,"column":2061}},{"source":"../node_modules/draft-js/lib/insertFragmentIntoContentState.js","name":"push","original":{"line":206,"column":16},"generated":{"line":1,"column":2066}},{"source":"../node_modules/draft-js/lib/insertFragmentIntoContentState.js","name":"push","original":{"line":206,"column":16},"generated":{"line":1,"column":2068}},{"source":"../node_modules/draft-js/lib/insertFragmentIntoContentState.js","name":"updateTail","original":{"line":206,"column":21},"generated":{"line":1,"column":2073}},{"source":"../node_modules/draft-js/lib/insertFragmentIntoContentState.js","name":"block","original":{"line":206,"column":32},"generated":{"line":1,"column":2075}},{"source":"../node_modules/draft-js/lib/insertFragmentIntoContentState.js","name":"targetOffset","original":{"line":206,"column":39},"generated":{"line":1,"column":2077}},{"source":"../node_modules/draft-js/lib/insertFragmentIntoContentState.js","name":"fragment","original":{"line":206,"column":53},"generated":{"line":1,"column":2079}},{"source":"../node_modules/draft-js/lib/insertFragmentIntoContentState.js","name":"push","original":{"line":186,"column":18},"generated":{"line":1,"column":2084}},{"source":"../node_modules/draft-js/lib/insertFragmentIntoContentState.js","name":"push","original":{"line":186,"column":18},"generated":{"line":1,"column":2086}},{"source":"../node_modules/draft-js/lib/insertFragmentIntoContentState.js","name":"block","original":{"line":186,"column":23},"generated":{"line":1,"column":2091}},{"source":"../node_modules/draft-js/lib/insertFragmentIntoContentState.js","name":"updatedBlockMap","original":{"line":209,"column":6},"generated":{"line":1,"column":2096}},{"source":"../node_modules/draft-js/lib/insertFragmentIntoContentState.js","name":"updatedBlockMap","original":{"line":209,"column":6},"generated":{"line":1,"column":2100}},{"source":"../node_modules/draft-js/lib/insertFragmentIntoContentState.js","name":"BlockMapBuilder","original":{"line":209,"column":24},"generated":{"line":1,"column":2102}},{"source":"../node_modules/draft-js/lib/insertFragmentIntoContentState.js","name":"createFromArray","original":{"line":209,"column":40},"generated":{"line":1,"column":2104}},{"source":"../node_modules/draft-js/lib/insertFragmentIntoContentState.js","name":"newBlockArr","original":{"line":209,"column":56},"generated":{"line":1,"column":2120}},{"source":"../node_modules/draft-js/lib/insertFragmentIntoContentState.js","name":"contentState","original":{"line":215,"column":9},"generated":{"line":1,"column":2123}},{"source":"../node_modules/draft-js/lib/insertFragmentIntoContentState.js","name":"isTreeBasedBlockMap","original":{"line":211,"column":6},"generated":{"line":1,"column":2130}},{"source":"../node_modules/draft-js/lib/insertFragmentIntoContentState.js","name":"updateBlockMapLinks","original":{"line":212,"column":22},"generated":{"line":1,"column":2134}},{"source":"../node_modules/draft-js/lib/insertFragmentIntoContentState.js","name":"updateBlockMapLinks","original":{"line":212,"column":22},"generated":{"line":1,"column":2136}},{"source":"../node_modules/draft-js/lib/insertFragmentIntoContentState.js","name":"updatedBlockMap","original":{"line":212,"column":42},"generated":{"line":1,"column":2138}},{"source":"../node_modules/draft-js/lib/insertFragmentIntoContentState.js","name":"blockMap","original":{"line":212,"column":59},"generated":{"line":1,"column":2140}},{"source":"../node_modules/draft-js/lib/insertFragmentIntoContentState.js","name":"target","original":{"line":212,"column":69},"generated":{"line":1,"column":2142}},{"source":"../node_modules/draft-js/lib/insertFragmentIntoContentState.js","name":"head","original":{"line":212,"column":77},"generated":{"line":1,"column":2144}},{"source":"../node_modules/draft-js/lib/insertFragmentIntoContentState.js","name":"contentState","original":{"line":215,"column":9},"generated":{"line":1,"column":2148}},{"source":"../node_modules/draft-js/lib/insertFragmentIntoContentState.js","name":"merge","original":{"line":215,"column":22},"generated":{"line":1,"column":2150}},{"source":"../node_modules/draft-js/lib/insertFragmentIntoContentState.js","original":{"line":215,"column":28},"generated":{"line":1,"column":2156}},{"source":"../node_modules/draft-js/lib/insertFragmentIntoContentState.js","name":"updatedBlockMap","original":{"line":216,"column":14},"generated":{"line":1,"column":2157}},{"source":"../node_modules/draft-js/lib/insertFragmentIntoContentState.js","name":"updatedBlockMap","original":{"line":216,"column":14},"generated":{"line":1,"column":2166}},{"source":"../node_modules/draft-js/lib/insertFragmentIntoContentState.js","name":"selectionState","original":{"line":217,"column":21},"generated":{"line":1,"column":2168}},{"source":"../node_modules/draft-js/lib/insertFragmentIntoContentState.js","name":"selectionState","original":{"line":217,"column":21},"generated":{"line":1,"column":2184}},{"source":"../node_modules/draft-js/lib/insertFragmentIntoContentState.js","name":"selectionState","original":{"line":218,"column":20},"generated":{"line":1,"column":2186}},{"source":"../node_modules/draft-js/lib/insertFragmentIntoContentState.js","name":"selectionState","original":{"line":218,"column":20},"generated":{"line":1,"column":2201}},{"source":"../node_modules/draft-js/lib/insertFragmentIntoContentState.js","name":"merge","original":{"line":218,"column":35},"generated":{"line":1,"column":2203}},{"source":"../node_modules/draft-js/lib/insertFragmentIntoContentState.js","original":{"line":218,"column":41},"generated":{"line":1,"column":2209}},{"source":"../node_modules/draft-js/lib/insertFragmentIntoContentState.js","name":"finalKey","original":{"line":219,"column":17},"generated":{"line":1,"column":2210}},{"source":"../node_modules/draft-js/lib/insertFragmentIntoContentState.js","name":"finalKey","original":{"line":219,"column":17},"generated":{"line":1,"column":2220}},{"source":"../node_modules/draft-js/lib/insertFragmentIntoContentState.js","name":"finalOffset","original":{"line":220,"column":20},"generated":{"line":1,"column":2222}},{"source":"../node_modules/draft-js/lib/insertFragmentIntoContentState.js","name":"finalOffset","original":{"line":220,"column":20},"generated":{"line":1,"column":2235}},{"source":"../node_modules/draft-js/lib/insertFragmentIntoContentState.js","name":"finalKey","original":{"line":221,"column":16},"generated":{"line":1,"column":2237}},{"source":"../node_modules/draft-js/lib/insertFragmentIntoContentState.js","name":"finalKey","original":{"line":221,"column":16},"generated":{"line":1,"column":2246}},{"source":"../node_modules/draft-js/lib/insertFragmentIntoContentState.js","name":"finalOffset","original":{"line":222,"column":19},"generated":{"line":1,"column":2248}},{"source":"../node_modules/draft-js/lib/insertFragmentIntoContentState.js","name":"finalOffset","original":{"line":222,"column":19},"generated":{"line":1,"column":2260}},{"source":"../node_modules/draft-js/lib/insertFragmentIntoContentState.js","original":{"line":223,"column":18},"generated":{"line":1,"column":2262}},{"source":"../node_modules/draft-js/lib/insertFragmentIntoContentState.js","original":{"line":223,"column":18},"generated":{"line":1,"column":2274}},{"source":"../node_modules/draft-js/lib/insertFragmentIntoContentState.js","name":"insertFragmentIntoContentState","original":{"line":228,"column":4},"generated":{"line":1,"column":2281}},{"source":"../node_modules/draft-js/lib/insertFragmentIntoContentState.js","original":{"line":228,"column":37},"generated":{"line":1,"column":2283}},{"source":"../node_modules/draft-js/lib/insertFragmentIntoContentState.js","name":"contentState","original":{"line":228,"column":77},"generated":{"line":1,"column":2292}},{"source":"../node_modules/draft-js/lib/insertFragmentIntoContentState.js","name":"selectionState","original":{"line":228,"column":91},"generated":{"line":1,"column":2294}},{"source":"../node_modules/draft-js/lib/insertFragmentIntoContentState.js","name":"fragmentBlockMap","original":{"line":228,"column":107},"generated":{"line":1,"column":2296}},{"source":"../node_modules/draft-js/lib/insertFragmentIntoContentState.js","name":"selectionState","original":{"line":229,"column":3},"generated":{"line":1,"column":2299}},{"source":"../node_modules/draft-js/lib/insertFragmentIntoContentState.js","name":"isCollapsed","original":{"line":229,"column":18},"generated":{"line":1,"column":2301}},{"source":"../node_modules/draft-js/lib/insertFragmentIntoContentState.js","name":"invariant","original":{"line":229,"column":169},"generated":{"line":1,"column":2316}},{"source":"../node_modules/draft-js/lib/insertFragmentIntoContentState.js","original":{"line":229,"column":179},"generated":{"line":1,"column":2319}},{"source":"../node_modules/draft-js/lib/insertFragmentIntoContentState.js","name":"blockMap","original":{"line":231,"column":6},"generated":{"line":1,"column":2322}},{"source":"../node_modules/draft-js/lib/insertFragmentIntoContentState.js","name":"blockMap","original":{"line":231,"column":6},"generated":{"line":1,"column":2326}},{"source":"../node_modules/draft-js/lib/insertFragmentIntoContentState.js","name":"contentState","original":{"line":231,"column":17},"generated":{"line":1,"column":2328}},{"source":"../node_modules/draft-js/lib/insertFragmentIntoContentState.js","name":"getBlockMap","original":{"line":231,"column":30},"generated":{"line":1,"column":2330}},{"source":"../node_modules/draft-js/lib/insertFragmentIntoContentState.js","name":"fragment","original":{"line":232,"column":6},"generated":{"line":1,"column":2344}},{"source":"../node_modules/draft-js/lib/insertFragmentIntoContentState.js","name":"randomizeBlockMapKeys","original":{"line":232,"column":17},"generated":{"line":1,"column":2346}},{"source":"../node_modules/draft-js/lib/insertFragmentIntoContentState.js","name":"fragmentBlockMap","original":{"line":232,"column":39},"generated":{"line":1,"column":2348}},{"source":"../node_modules/draft-js/lib/insertFragmentIntoContentState.js","name":"targetKey","original":{"line":233,"column":6},"generated":{"line":1,"column":2351}},{"source":"../node_modules/draft-js/lib/insertFragmentIntoContentState.js","name":"selectionState","original":{"line":233,"column":18},"generated":{"line":1,"column":2353}},{"source":"../node_modules/draft-js/lib/insertFragmentIntoContentState.js","name":"getStartKey","original":{"line":233,"column":33},"generated":{"line":1,"column":2355}},{"source":"../node_modules/draft-js/lib/insertFragmentIntoContentState.js","name":"targetOffset","original":{"line":234,"column":6},"generated":{"line":1,"column":2369}},{"source":"../node_modules/draft-js/lib/insertFragmentIntoContentState.js","name":"selectionState","original":{"line":234,"column":21},"generated":{"line":1,"column":2371}},{"source":"../node_modules/draft-js/lib/insertFragmentIntoContentState.js","name":"getStartOffset","original":{"line":234,"column":36},"generated":{"line":1,"column":2373}},{"source":"../node_modules/draft-js/lib/insertFragmentIntoContentState.js","name":"targetBlock","original":{"line":236,"column":6},"generated":{"line":1,"column":2390}},{"source":"../node_modules/draft-js/lib/insertFragmentIntoContentState.js","name":"blockMap","original":{"line":236,"column":20},"generated":{"line":1,"column":2392}},{"source":"../node_modules/draft-js/lib/insertFragmentIntoContentState.js","name":"get","original":{"line":236,"column":29},"generated":{"line":1,"column":2394}},{"source":"../node_modules/draft-js/lib/insertFragmentIntoContentState.js","name":"targetKey","original":{"line":236,"column":33},"generated":{"line":1,"column":2398}},{"source":"../node_modules/draft-js/lib/insertFragmentIntoContentState.js","name":"fragment","original":{"line":244,"column":6},"generated":{"line":1,"column":2401}},{"source":"../node_modules/draft-js/lib/insertFragmentIntoContentState.js","name":"targetBlock","original":{"line":238,"column":6},"generated":{"line":1,"column":2408}},{"source":"../node_modules/draft-js/lib/insertFragmentIntoContentState.js","name":"ContentBlockNode","original":{"line":238,"column":29},"generated":{"line":1,"column":2421}},{"source":"../node_modules/draft-js/lib/insertFragmentIntoContentState.js","name":"targetBlock","original":{"line":239,"column":5},"generated":{"line":1,"column":2425}},{"source":"../node_modules/draft-js/lib/insertFragmentIntoContentState.js","name":"getChildKeys","original":{"line":239,"column":17},"generated":{"line":1,"column":2427}},{"source":"../node_modules/draft-js/lib/insertFragmentIntoContentState.js","name":"isEmpty","original":{"line":239,"column":32},"generated":{"line":1,"column":2442}},{"source":"../node_modules/draft-js/lib/insertFragmentIntoContentState.js","name":"invariant","original":{"line":239,"column":179},"generated":{"line":1,"column":2453}},{"source":"../node_modules/draft-js/lib/insertFragmentIntoContentState.js","original":{"line":239,"column":189},"generated":{"line":1,"column":2456}},{"source":"../node_modules/draft-js/lib/insertFragmentIntoContentState.js","original":{"line":244,"column":24},"generated":{"line":1,"column":2460}},{"source":"../node_modules/draft-js/lib/insertFragmentIntoContentState.js","name":"fragment","original":{"line":244,"column":6},"generated":{"line":1,"column":2464}},{"source":"../node_modules/draft-js/lib/insertFragmentIntoContentState.js","name":"size","original":{"line":244,"column":15},"generated":{"line":1,"column":2466}},{"source":"../node_modules/draft-js/lib/insertFragmentIntoContentState.js","name":"updateExistingBlock","original":{"line":245,"column":11},"generated":{"line":1,"column":2471}},{"source":"../node_modules/draft-js/lib/insertFragmentIntoContentState.js","name":"contentState","original":{"line":245,"column":31},"generated":{"line":1,"column":2473}},{"source":"../node_modules/draft-js/lib/insertFragmentIntoContentState.js","name":"selectionState","original":{"line":245,"column":45},"generated":{"line":1,"column":2475}},{"source":"../node_modules/draft-js/lib/insertFragmentIntoContentState.js","name":"blockMap","original":{"line":245,"column":61},"generated":{"line":1,"column":2477}},{"source":"../node_modules/draft-js/lib/insertFragmentIntoContentState.js","name":"fragment","original":{"line":245,"column":71},"generated":{"line":1,"column":2479}},{"source":"../node_modules/draft-js/lib/insertFragmentIntoContentState.js","name":"first","original":{"line":245,"column":80},"generated":{"line":1,"column":2481}},{"source":"../node_modules/draft-js/lib/insertFragmentIntoContentState.js","name":"targetKey","original":{"line":245,"column":89},"generated":{"line":1,"column":2489}},{"source":"../node_modules/draft-js/lib/insertFragmentIntoContentState.js","name":"targetOffset","original":{"line":245,"column":100},"generated":{"line":1,"column":2491}},{"source":"../node_modules/draft-js/lib/insertFragmentIntoContentState.js","name":"insertFragment","original":{"line":248,"column":9},"generated":{"line":1,"column":2494}},{"source":"../node_modules/draft-js/lib/insertFragmentIntoContentState.js","name":"contentState","original":{"line":248,"column":24},"generated":{"line":1,"column":2496}},{"source":"../node_modules/draft-js/lib/insertFragmentIntoContentState.js","name":"selectionState","original":{"line":248,"column":38},"generated":{"line":1,"column":2498}},{"source":"../node_modules/draft-js/lib/insertFragmentIntoContentState.js","name":"blockMap","original":{"line":248,"column":54},"generated":{"line":1,"column":2500}},{"source":"../node_modules/draft-js/lib/insertFragmentIntoContentState.js","name":"fragment","original":{"line":248,"column":64},"generated":{"line":1,"column":2502}},{"source":"../node_modules/draft-js/lib/insertFragmentIntoContentState.js","name":"targetKey","original":{"line":248,"column":74},"generated":{"line":1,"column":2504}},{"source":"../node_modules/draft-js/lib/insertFragmentIntoContentState.js","name":"targetOffset","original":{"line":248,"column":85},"generated":{"line":1,"column":2506}},{"source":"../node_modules/draft-js/lib/insertFragmentIntoContentState.js","name":"module","original":{"line":251,"column":0},"generated":{"line":1,"column":2510}},{"source":"../node_modules/draft-js/lib/insertFragmentIntoContentState.js","name":"exports","original":{"line":251,"column":7},"generated":{"line":1,"column":2517}},{"source":"../node_modules/draft-js/lib/insertFragmentIntoContentState.js","name":"insertFragmentIntoContentState","original":{"line":251,"column":17},"generated":{"line":1,"column":2525}}],"sources":{"../node_modules/draft-js/lib/insertFragmentIntoContentState.js":"/**\n * Copyright (c) 2013-present, Facebook, Inc.\n * All rights reserved.\n *\n * This source code is licensed under the BSD-style license found in the\n * LICENSE file in the root directory of this source tree. An additional grant\n * of patent rights can be found in the PATENTS file in the same directory.\n *\n * @providesModule insertFragmentIntoContentState\n * @format\n * \n */\n\n'use strict';\n\nvar BlockMapBuilder = require('./BlockMapBuilder');\nvar ContentBlockNode = require('./ContentBlockNode');\nvar Immutable = require('immutable');\n\nvar insertIntoList = require('./insertIntoList');\nvar invariant = require('fbjs/lib/invariant');\nvar randomizeBlockMapKeys = require('./randomizeBlockMapKeys');\n\nvar List = Immutable.List;\n\n\nvar updateExistingBlock = function updateExistingBlock(contentState, selectionState, blockMap, fragmentBlock, targetKey, targetOffset) {\n  var targetBlock = blockMap.get(targetKey);\n  var text = targetBlock.getText();\n  var chars = targetBlock.getCharacterList();\n  var finalKey = targetKey;\n  var finalOffset = targetOffset + fragmentBlock.getText().length;\n\n  var newBlock = targetBlock.merge({\n    text: text.slice(0, targetOffset) + fragmentBlock.getText() + text.slice(targetOffset),\n    characterList: insertIntoList(chars, fragmentBlock.getCharacterList(), targetOffset),\n    data: fragmentBlock.getData()\n  });\n\n  return contentState.merge({\n    blockMap: blockMap.set(targetKey, newBlock),\n    selectionBefore: selectionState,\n    selectionAfter: selectionState.merge({\n      anchorKey: finalKey,\n      anchorOffset: finalOffset,\n      focusKey: finalKey,\n      focusOffset: finalOffset,\n      isBackward: false\n    })\n  });\n};\n\n/**\n * Appends text/characterList from the fragment first block to\n * target block.\n */\nvar updateHead = function updateHead(block, targetOffset, fragment) {\n  var text = block.getText();\n  var chars = block.getCharacterList();\n\n  // Modify head portion of block.\n  var headText = text.slice(0, targetOffset);\n  var headCharacters = chars.slice(0, targetOffset);\n  var appendToHead = fragment.first();\n\n  return block.merge({\n    text: headText + appendToHead.getText(),\n    characterList: headCharacters.concat(appendToHead.getCharacterList()),\n    type: headText ? block.getType() : appendToHead.getType(),\n    data: appendToHead.getData()\n  });\n};\n\n/**\n * Appends offset text/characterList from the target block to the last\n * fragment block.\n */\nvar updateTail = function updateTail(block, targetOffset, fragment) {\n  // Modify tail portion of block.\n  var text = block.getText();\n  var chars = block.getCharacterList();\n\n  // Modify head portion of block.\n  var blockSize = text.length;\n  var tailText = text.slice(targetOffset, blockSize);\n  var tailCharacters = chars.slice(targetOffset, blockSize);\n  var prependToTail = fragment.last();\n\n  return prependToTail.merge({\n    text: prependToTail.getText() + tailText,\n    characterList: prependToTail.getCharacterList().concat(tailCharacters),\n    data: prependToTail.getData()\n  });\n};\n\nvar getRootBlocks = function getRootBlocks(block, blockMap) {\n  var headKey = block.getKey();\n  var rootBlock = block;\n  var rootBlocks = [];\n\n  // sometimes the fragment head block will not be part of the blockMap itself this can happen when\n  // the fragment head is used to update the target block, however when this does not happen we need\n  // to make sure that we include it on the rootBlocks since the first block of a fragment is always a\n  // fragment root block\n  if (blockMap.get(headKey)) {\n    rootBlocks.push(headKey);\n  }\n\n  while (rootBlock && rootBlock.getNextSiblingKey()) {\n    var lastSiblingKey = rootBlock.getNextSiblingKey();\n\n    if (!lastSiblingKey) {\n      break;\n    }\n\n    rootBlocks.push(lastSiblingKey);\n    rootBlock = blockMap.get(lastSiblingKey);\n  }\n\n  return rootBlocks;\n};\n\nvar updateBlockMapLinks = function updateBlockMapLinks(blockMap, originalBlockMap, targetBlock, fragmentHeadBlock) {\n  return blockMap.withMutations(function (blockMapState) {\n    var targetKey = targetBlock.getKey();\n    var headKey = fragmentHeadBlock.getKey();\n    var targetNextKey = targetBlock.getNextSiblingKey();\n    var targetParentKey = targetBlock.getParentKey();\n    var fragmentRootBlocks = getRootBlocks(fragmentHeadBlock, blockMap);\n    var lastRootFragmentBlockKey = fragmentRootBlocks[fragmentRootBlocks.length - 1];\n\n    if (blockMapState.get(headKey)) {\n      // update the fragment head when it is part of the blockMap otherwise\n      blockMapState.setIn([targetKey, 'nextSibling'], headKey);\n      blockMapState.setIn([headKey, 'prevSibling'], targetKey);\n    } else {\n      // update the target block that had the fragment head contents merged into it\n      blockMapState.setIn([targetKey, 'nextSibling'], fragmentHeadBlock.getNextSiblingKey());\n      blockMapState.setIn([fragmentHeadBlock.getNextSiblingKey(), 'prevSibling'], targetKey);\n    }\n\n    // update the last root block fragment\n    blockMapState.setIn([lastRootFragmentBlockKey, 'nextSibling'], targetNextKey);\n\n    // update the original target next block\n    if (targetNextKey) {\n      blockMapState.setIn([targetNextKey, 'prevSibling'], lastRootFragmentBlockKey);\n    }\n\n    // update fragment parent links\n    fragmentRootBlocks.forEach(function (blockKey) {\n      return blockMapState.setIn([blockKey, 'parent'], targetParentKey);\n    });\n\n    // update targetBlock parent child links\n    if (targetParentKey) {\n      var targetParent = blockMap.get(targetParentKey);\n      var originalTargetParentChildKeys = targetParent.getChildKeys();\n\n      var targetBlockIndex = originalTargetParentChildKeys.indexOf(targetKey);\n      var insertionIndex = targetBlockIndex + 1;\n\n      var newChildrenKeysArray = originalTargetParentChildKeys.toArray();\n\n      // insert fragment children\n      newChildrenKeysArray.splice.apply(newChildrenKeysArray, [insertionIndex, 0].concat(fragmentRootBlocks));\n\n      blockMapState.setIn([targetParentKey, 'children'], List(newChildrenKeysArray));\n    }\n  });\n};\n\nvar insertFragment = function insertFragment(contentState, selectionState, blockMap, fragment, targetKey, targetOffset) {\n  var isTreeBasedBlockMap = blockMap.first() instanceof ContentBlockNode;\n  var newBlockArr = [];\n  var fragmentSize = fragment.size;\n  var target = blockMap.get(targetKey);\n  var head = fragment.first();\n  var tail = fragment.last();\n  var finalOffset = tail.getLength();\n  var finalKey = tail.getKey();\n  var shouldNotUpdateFromFragmentBlock = isTreeBasedBlockMap && (!target.getChildKeys().isEmpty() || !head.getChildKeys().isEmpty());\n\n  blockMap.forEach(function (block, blockKey) {\n    if (blockKey !== targetKey) {\n      newBlockArr.push(block);\n      return;\n    }\n\n    if (shouldNotUpdateFromFragmentBlock) {\n      newBlockArr.push(block);\n    } else {\n      newBlockArr.push(updateHead(block, targetOffset, fragment));\n    }\n\n    // Insert fragment blocks after the head and before the tail.\n    fragment\n    // when we are updating the target block with the head fragment block we skip the first fragment\n    // head since its contents have already been merged with the target block otherwise we include\n    // the whole fragment\n    .slice(shouldNotUpdateFromFragmentBlock ? 0 : 1, fragmentSize - 1).forEach(function (fragmentBlock) {\n      return newBlockArr.push(fragmentBlock);\n    });\n\n    // update tail\n    newBlockArr.push(updateTail(block, targetOffset, fragment));\n  });\n\n  var updatedBlockMap = BlockMapBuilder.createFromArray(newBlockArr);\n\n  if (isTreeBasedBlockMap) {\n    updatedBlockMap = updateBlockMapLinks(updatedBlockMap, blockMap, target, head);\n  }\n\n  return contentState.merge({\n    blockMap: updatedBlockMap,\n    selectionBefore: selectionState,\n    selectionAfter: selectionState.merge({\n      anchorKey: finalKey,\n      anchorOffset: finalOffset,\n      focusKey: finalKey,\n      focusOffset: finalOffset,\n      isBackward: false\n    })\n  });\n};\n\nvar insertFragmentIntoContentState = function insertFragmentIntoContentState(contentState, selectionState, fragmentBlockMap) {\n  !selectionState.isCollapsed() ? process.env.NODE_ENV !== 'production' ? invariant(false, '`insertFragment` should only be called with a collapsed selection state.') : invariant(false) : void 0;\n\n  var blockMap = contentState.getBlockMap();\n  var fragment = randomizeBlockMapKeys(fragmentBlockMap);\n  var targetKey = selectionState.getStartKey();\n  var targetOffset = selectionState.getStartOffset();\n\n  var targetBlock = blockMap.get(targetKey);\n\n  if (targetBlock instanceof ContentBlockNode) {\n    !targetBlock.getChildKeys().isEmpty() ? process.env.NODE_ENV !== 'production' ? invariant(false, '`insertFragment` should not be called when a container node is selected.') : invariant(false) : void 0;\n  }\n\n  // When we insert a fragment with a single block we simply update the target block\n  // with the contents of the inserted fragment block\n  if (fragment.size === 1) {\n    return updateExistingBlock(contentState, selectionState, blockMap, fragment.first(), targetKey, targetOffset);\n  }\n\n  return insertFragment(contentState, selectionState, blockMap, fragment, targetKey, targetOffset);\n};\n\nmodule.exports = insertFragmentIntoContentState;"},"lineCount":null}},"hash":"d1ea0689615a5f2560db7b76a8fdac05","cacheData":{"env":{"NODE_ENV":"production"}}}